{
  "receipt_id": "107043fc-5095-4f66-a05b-b4e5694df1f9",
  "moneyAmount": 8270.99,
  "amountFromDocument": 8270.99,
  "subTotal": 7211.63,
  "totalTax": 1059.36,
  "priceIncludingTax": 8270.99,
  "discount": 0.0,
  "timeFromReceipt": "2024-09-02T11:22:00",
  "company": {
    "name": "H & M Hennes & Mauritz CZ s.r.o.",
    "companyCountryCode": "CZ"
  },
  "shop": {
    "addressStreet": "Budějovická",
    "addressStreetNumber": "1667/64",
    "addressMunicipality": "Praha 4",
    "addressZip": "14000"
  },
  "currency": "CZK",
  "status": "DONE",
  "source": "ANDROID_RECEIPT_UPLOAD",
  "exchangeRate": null,
  "items": [
    {
      "name": "Rámeček na foto 21x30",
      "pricePerUnit": 161.03,
      "quantity": 1.0,
      "itemCategory": "Home Decor",
      "quantityUnit": "ks",
      "subTotal": 133.08,
      "tax": 27.95,
      "taxPercentage": 21.0,
      "priceIncludingTax": 161.03,
      "discount": null,
      "discountDescriptive": "",
      "priceTotal": 161.03,
      "success": true,
      "index": 0,
      "notices": []
    },
    {
      "name": "Yoga podložka 6mm",
      "pricePerUnit": 391.83,
      "quantity": 1.0,
      "itemCategory": "Sporting Goods",
      "quantityUnit": "ks",
      "subTotal": 340.72,
      "tax": null,
      "taxPercentage": 15.0,
      "priceIncludingTax": 391.83,
      "discount": null,
      "discountDescriptive": "",
      "priceTotal": 391.83,
      "success": true,
      "index": 1,
      "notices": []
    },
    {
      "name": "Svíčka vanilková",
      "pricePerUnit": 221.58,
      "quantity": 1.0,
      "itemCategory": "Home Decor",
      "quantityUnit": "ks",
      "subTotal": 201.44,
      "tax": 20.14,
      "taxPercentage": 10.0,
      "priceIncludingTax": 221.58,
      "discount": null,
      "discountDescriptive": "",
      "priceTotal": 221.58,
      "success": true,
      "index": 2,
      "notices": []
    },
    {
      "name": "Cyklistická přilba",
      "pricePerUnit": 520.35,
      "quantity": 1.0,
      "itemCategory": "Sporting Goods",
      "quantityUnit": "ks",
      "subTotal": 452.48,
      "tax": 67.87,
      "taxPercentage": 15.0,
      "priceIncludingTax": 520.35,
      "discount": null,
      "discountDescriptive": "",
      "priceTotal": 520.35,
      "success": true,
      "index": 3,
      "notices": []
    },
    {
      "name": "Cyklistická přilba",
      "pricePerUnit": 545.11,
      "quantity": 1.0,
      "itemCategory": "Sporting Goods",
      "quantityUnit": "ks",
      "subTotal": 474.01,
      "tax": 71.1,
      "taxPercentage": 15.0,
      "priceIncludingTax": 545.11,
      "discount": null,
      "discountDescriptive": "",
      "priceTotal": 545.11,
      "success": true,
      "index": 4,
      "notices": []
    },
    {
      "name": "Polštář 50x50",
      "pricePerUnit": 278.43,
      "quantity": 2.0,
      "itemCategory": "Home Decor",
      "quantityUnit": "ks",
      "subTotal": 506.24,
      "tax": 50.62,
      "taxPercentage": 10.0,
      "priceIncludingTax": 556.86,
      "discount": null,
      "discountDescriptive": "",
      "priceTotal": 556.86,
      "success": true,
      "index": 5,
      "notices": []
    },
    {
      "name": "Cykulistická přilba",
      "pricePerUnit": 547.34,
      "quantity": 1.0,
      "itemCategory": "Sporting Goods",
      "quantityUnit": "ks",
      "subTotal": 497.58,
      "tax": 49.76,
      "taxPercentage": 10.0,
      "priceIncludingTax": 547.34,
      "discount": null,
      "discountDescriptive": "",
      "priceTotal": 547.34,
      "success": true,
      "index": 6,
      "notices": []
    },
    {
      "name": "Kuchyňský nůž",
      "pricePerUnit": 563.64,
      "quantity": 2.0,
      "itemCategory": "Household Supplies",
      "quantityUnit": "ks",
      "subTotal": 931.64,
      "tax": 195.64,
      "taxPercentage": 21.0,
      "priceIncludingTax": 1127.28,
      "discount": null,
      "discountDescriptive": "",
      "priceTotal": 1127.28,
      "success": true,
      "index": 7,
      "notices": []
    },
    {
      "name": "Kuchyňský nůž",
      "pricePerUnit": 446.74,
      "quantity": 2.0,
      "itemCategory": "Household Supplies",
      "quantityUnit": "ks",
      "subTotal": 812.25,
      "tax": 81.23,
      "taxPercentage": 10.0,
      "priceIncludingTax": 893.48,
      "discount": null,
      "discountDescriptive": "",
      "priceTotal": 903.08,
      "success": true,
      "index": 8,
      "notices": []
    },
    {
      "name": "Cyklistická přilba",
      "pricePerUnit": 611.12,
      "quantity": 1.0,
      "itemCategory": "Sporting Goods",
      "quantityUnit": "ks",
      "subTotal": 505.06,
      "tax": 106.06,
      "taxPercentage": 21.0,
      "priceIncludingTax": 611.12,
      "discount": null,
      "discountDescriptive": "",
      "priceTotal": 611.12,
      "success": true,
      "index": 9,
      "notices": []
    },
    {
      "name": "Kuchyňský nůž",
      "pricePerUnit": 561.48,
      "quantity": 1.0,
      "itemCategory": "Household Supplies",
      "quantityUnit": "ks",
      "subTotal": 464.03,
      "tax": 97.45,
      "taxPercentage": 21.0,
      "priceIncludingTax": 561.48,
      "discount": null,
      "discountDescriptive": "",
      "priceTotal": 561.48,
      "success": true,
      "index": 10,
      "notices": []
    },
    {
      "name": "Yoga podložka 6mm",
      "pricePerUnit": 418.23,
      "quantity": 2.0,
      "itemCategory": "Sporting Goods",
      "quantityUnit": "ks",
      "subTotal": 691.29,
      "tax": 145.17,
      "taxPercentage": 21.0,
      "priceIncludingTax": 836.46,
      "discount": null,
      "discountDescriptive": "",
      "priceTotal": 836.46,
      "success": true,
      "index": 11,
      "notices": []
    },
    {
      "name": "Rámeček na foto 21x30",
      "pricePerUnit": 153.62,
      "quantity": 1.0,
      "itemCategory": "Home Decor",
      "quantityUnit": "ks",
      "subTotal": 139.65,
      "tax": 13.97,
      "taxPercentage": 10.0,
      "priceIncludingTax": 153.62,
      "discount": null,
      "discountDescriptive": "",
      "priceTotal": 153.62,
      "success": true,
      "index": 12,
      "notices": []
    },
    {
      "name": "Yoga podložka 6mm",
      "pricePerUnit": 392.05,
      "quantity": 1.0,
      "itemCategory": "Sporting Goods",
      "quantityUnit": "ks",
      "subTotal": 356.41,
      "tax": 35.64,
      "taxPercentage": 10.0,
      "priceIncludingTax": 392.05,
      "discount": null,
      "discountDescriptive": "",
      "priceTotal": 392.05,
      "success": true,
      "index": 13,
      "notices": []
    },
    {
      "name": "Džíny slikm 32/32",
      "pricePerUnit": 741.8,
      "quantity": 1.0,
      "itemCategory": "Clothing",
      "quantityUnit": "ks",
      "subTotal": 645.04,
      "tax": 96.76,
      "taxPercentage": 15.0,
      "priceIncludingTax": 741.8,
      "discount": null,
      "discountDescriptive": "",
      "priceTotal": 741.8,
      "success": true,
      "index": 14,
      "notices": []
    }
  ],
  "notices": [
    {
      "type": "TOTAL_AMOUNT_CONFLICT",
      "status": "NEW"
    }
  ],
  "_metrics": {
    "cer": 2.566,
    "f1_items": 93.927,
    "length_category": "mid",
    "n_items_groundtruth": 15
  }
}