{
  "receipt_id": "745e1c82-d62e-477c-a419-ceb2f268c541",
  "moneyAmount": 504.63,
  "amountFromDocument": 504.63,
  "subTotal": 456.82,
  "totalTax": 47.81,
  "priceIncludingTax": 504.63,
  "discount": 0.0,
  "timeFromReceipt": "2025-05-12T20:53:00",
  "company": {
    "name": "TETA drogerie s.r.o.",
    "companyCountryCode": "CZ"
  },
  "shop": {
    "addressStreet": "Chodov",
    "addressStreetNumber": "2280/1",
    "addressMunicipality": "Praha 11",
    "addressZip": "14900"
  },
  "currency": "CZK",
  "status": "DONE",
  "source": "ANDROID_RECEIPT_UPLOAD",
  "exchangeRate": null,
  "items": [
    {
      "name": "Deodorant Rexona 150ml",
      "pricePerUnit": 73.12,
      "quantity": 1.0,
      "itemCategory": "Personal Care",
      "quantityUnit": "ks",
      "subTotal": 66.47,
      "tax": 6.65,
      "taxPercentage": 10.0,
      "priceIncludingTax": 73.12,
      "discount": null,
      "discountDescriptive": "",
      "priceTotal": 73.12,
      "success": true,
      "index": 0,
      "notices": []
    },
    {
      "name": "Zubní pasta Colgate 75ml",
      "pricePerUnit": 48.94,
      "quantity": 1.0,
      "itemCategory": "",
      "quantityUnit": "ks",
      "subTotal": 42.56,
      "tax": 6.38,
      "taxPercentage": 15.0,
      "priceIncludingTax": 48.94,
      "discount": null,
      "discountDescriptive": "",
      "priceTotal": 48.94,
      "success": true,
      "index": 1,
      "notices": []
    },
    {
      "name": "Rukavtice latex M 100ks",
      "pricePerUnit": 135.66,
      "quantity": 1.0,
      "itemCategory": "Household Supplies",
      "quantityUnit": "ks",
      "subTotal": null,
      "tax": 12.33,
      "taxPercentage": 10.0,
      "priceIncludingTax": 135.66,
      "discount": null,
      "discountDescriptive": "",
      "priceTotal": 135.66,
      "success": true,
      "index": 2,
      "notices": []
    },
    {
      "name": "Bavlněné tampony 100ks",
      "pricePerUnit": 54.93,
      "quantity": 3.0,
      "itemCategory": "Personal Care",
      "quantityUnit": "ks",
      "subTotal": 149.81,
      "tax": 14.98,
      "taxPercentage": 10.0,
      "priceIncludingTax": 164.79,
      "discount": null,
      "discountDescriptive": "",
      "priceTotal": 164.79,
      "success": true,
      "index": 3,
      "notices": []
    },
    {
      "name": "Zubní kartáček",
      "pricePerUnit": 41.06,
      "quantity": 2.0,
      "itemCategory": "Personal Care",
      "quantityUnit": "ks",
      "subTotal": 74.65,
      "tax": 7.47,
      "taxPercentage": 10.0,
      "priceIncludingTax": 82.12,
      "discount": null,
      "discountDescriptive": "",
      "priceTotal": 82.12,
      "success": true,
      "index": 4,
      "notices": []
    }
  ],
  "notices": [],
  "_metrics": {
    "cer": 4.08,
    "f1_items": 97.195,
    "length_category": "short",
    "n_items_groundtruth": 5
  }
}