{
  "receipt_id": "3049f849-3caf-4c51-917e-f8b9979a1c10",
  "moneyAmount": 1187.04,
  "amountFromDocument": 1187.04,
  "subTotal": 1042.45,
  "totalTax": 144.59,
  "priceIncludingTax": 1187.04,
  "discount": 0.0,
  "timeFromReceipt": "2024-06-27T19:52:00",
  "company": {
    "name": "PENNY s.r.o.",
    "companyCountryCode": "CZ"
  },
  "shop": {
    "addressStreet": "Palladium",
    "addressStreetNumber": "377/1",
    "addressMunicipality": "Praha 1",
    "addressZip": "11000"
  },
  "currency": "CZK",
  "status": "DONE",
  "source": "ANDROID_RECEIPT_UPLOAD",
  "exchangeRate": null,
  "items": [
    {
      "name": "Toaletní papír 8ks",
      "pricePerUnit": 66.22,
      "quantity": 1.0,
      "itemCategory": "Household Supplies",
      "quantityUnit": "ks",
      "subTotal": 54.73,
      "tax": 11.49,
      "taxPercentage": 21.0,
      "priceIncludingTax": 66.22,
      "discount": null,
      "discountDescriptive": "",
      "priceTotal": 68.74,
      "success": true,
      "index": 0,
      "notices": []
    },
    {
      "name": "Jogurt bílý 150g",
      "pricePerUnit": 9.24,
      "quantity": 2.0,
      "itemCategory": "Dairy Products",
      "quantityUnit": "ks",
      "subTotal": 15.27,
      "tax": null,
      "taxPercentage": 21.0,
      "priceIncludingTax": 18.48,
      "discount": null,
      "discountDescriptive": "",
      "priceTotal": 18.48,
      "success": true,
      "index": 1,
      "notices": []
    },
    {
      "name": "Kinder Bueno",
      "pricePerUnit": 21.75,
      "quantity": 1.0,
      "itemCategory": "Snacks",
      "quantityUnit": "ks",
      "subTotal": 19.77,
      "tax": 1.98,
      "taxPercentage": 10.0,
      "priceIncludingTax": 21.75,
      "discount": null,
      "discountDescriptive": "",
      "priceTotal": 21.75,
      "success": true,
      "index": 2,
      "notices": []
    },
    {
      "name": "Aviváž Lenor 1l",
      "pricePerUnit": 88.45,
      "quantity": 2.0,
      "itemCategory": "Household Supplies",
      "quantityUnit": "ks",
      "subTotal": 160.82,
      "tax": 16.08,
      "taxPercentage": 10.0,
      "priceIncludingTax": 176.9,
      "discount": null,
      "discountDescriptive": "",
      "priceTotal": 176.9,
      "success": true,
      "index": 3,
      "notices": []
    },
    {
      "name": "Pomeranče síťka 1kg",
      "pricePerUnit": 34.88,
      "quantity": 1.0,
      "itemCategory": "Fresh Products",
      "quantityUnit": "ks",
      "subTotal": 31.71,
      "tax": 3.17,
      "taxPercentage": 10.0,
      "priceIncludingTax": 34.88,
      "discount": null,
      "discountDescriptive": "",
      "priceTotal": 34.88,
      "success": true,
      "index": 4,
      "notices": []
    },
    {
      "name": "Ricotta 250g",
      "pricePerUnit": 43.73,
      "quantity": 1.0,
      "itemCategory": "Dairy Products",
      "quantityUnit": "ks",
      "subTotal": 38.03,
      "tax": 5.7,
      "taxPercentage": 15.0,
      "priceIncludingTax": 43.73,
      "discount": null,
      "discountDescriptive": "",
      "priceTotal": 43.73,
      "success": true,
      "index": 5,
      "notices": []
    },
    {
      "name": "Müsli tyčinka",
      "pricePerUnit": 11.2,
      "quantity": 3.0,
      "itemCategory": "Snacks",
      "quantityUnit": "ks",
      "subTotal": 30.55,
      "tax": null,
      "taxPercentage": 10.0,
      "priceIncludingTax": 33.6,
      "discount": null,
      "discountDescriptive": "",
      "priceTotal": 33.6,
      "success": true,
      "index": 6,
      "notices": []
    },
    {
      "name": "Cottage sýr 180g",
      "pricePerUnit": 31.28,
      "quantity": 3.0,
      "itemCategory": "",
      "quantityUnit": "ks",
      "subTotal": 81.6,
      "tax": null,
      "taxPercentage": 15.0,
      "priceIncludingTax": 93.84,
      "discount": null,
      "discountDescriptive": "",
      "priceTotal": 93.84,
      "success": false,
      "index": 7,
      "notices": []
    },
    {
      "name": "Rajčata cherry 250g",
      "pricePerUnit": 44.69,
      "quantity": 1.0,
      "itemCategory": "Vegetables",
      "quantityUnit": "ks",
      "subTotal": null,
      "tax": 7.76,
      "taxPercentage": 21.0,
      "priceIncludingTax": 44.69,
      "discount": null,
      "discountDescriptive": "",
      "priceTotal": 44.43,
      "success": true,
      "index": 8,
      "notices": []
    },
    {
      "name": "Cibule žlutá 1kg",
      "pricePerUnit": 21.15,
      "quantity": 1.0,
      "itemCategory": "Vegetables",
      "quantityUnit": "ks",
      "subTotal": 17.48,
      "tax": 3.67,
      "taxPercentage": 21.0,
      "priceIncludingTax": 21.15,
      "discount": null,
      "discountDescriptive": "",
      "priceTotal": 21.15,
      "success": true,
      "index": 9,
      "notices": []
    },
    {
      "name": "Máslo 250g",
      "pricePerUnit": 48.68,
      "quantity": 1.0,
      "itemCategory": "Dairy Products",
      "quantityUnit": "ks",
      "subTotal": 42.33,
      "tax": 6.35,
      "taxPercentage": 15.0,
      "priceIncludingTax": 48.68,
      "discount": null,
      "discountDescriptive": "",
      "priceTotal": 48.68,
      "success": true,
      "index": 10,
      "notices": []
    },
    {
      "name": "Chips Lay's 130g",
      "pricePerUnit": 25.78,
      "quantity": 1.0,
      "itemCategory": "Snacks",
      "quantityUnit": "ks",
      "subTotal": 23.44,
      "tax": 2.34,
      "taxPercentage": 10.0,
      "priceIncludingTax": 25.78,
      "discount": null,
      "discountDescriptive": "",
      "priceTotal": 25.78,
      "success": true,
      "index": 11,
      "notices": []
    },
    {
      "name": "Jar Yjkjuuv 500ml",
      "pricePerUnit": 38.03,
      "quantity": 1.0,
      "itemCategory": "Household Supplies",
      "quantityUnit": "ks",
      "subTotal": 33.07,
      "tax": 4.96,
      "taxPercentage": 15.0,
      "priceIncludingTax": 38.03,
      "discount": null,
      "discountDescriptive": "",
      "priceTotal": 38.03,
      "success": true,
      "index": 12,
      "notices": []
    },
    {
      "name": "Pivo Pilsner 0,5l",
      "pricePerUnit": 18.44,
      "quantity": 2.0,
      "itemCategory": "Beverages",
      "quantityUnit": "ks",
      "subTotal": 32.07,
      "tax": 4.81,
      "taxPercentage": 15.0,
      "priceIncludingTax": 36.88,
      "discount": null,
      "discountDescriptive": "",
      "priceTotal": 36.88,
      "success": true,
      "index": 13,
      "notices": []
    },
    {
      "name": "Džus pomeranč 1l",
      "pricePerUnit": 35.28,
      "quantity": 3.0,
      "itemCategory": "Beverages",
      "quantityUnit": "ks",
      "subTotal": 87.47,
      "tax": 18.37,
      "taxPercentage": 21.0,
      "priceIncludingTax": 105.84,
      "discount": null,
      "discountDescriptive": "",
      "priceTotal": 114.7,
      "success": true,
      "index": 14,
      "notices": []
    },
    {
      "name": "Jogurt bílý 150g",
      "pricePerUnit": 9.82,
      "quantity": 3.0,
      "itemCategory": "Dairy Products",
      "quantityUnit": "ks",
      "subTotal": 25.62,
      "tax": 3.84,
      "taxPercentage": 15.0,
      "priceIncludingTax": 29.46,
      "discount": null,
      "discountDescriptive": "",
      "priceTotal": 29.46,
      "success": true,
      "index": 15,
      "notices": []
    },
    {
      "name": "Ricotta 250g",
      "pricePerUnit": 38.42,
      "quantity": 1.0,
      "itemCategory": "Dairy Products",
      "quantityUnit": "ks",
      "subTotal": 31.75,
      "tax": 6.67,
      "taxPercentage": 21.0,
      "priceIncludingTax": 38.42,
      "discount": null,
      "discountDescriptive": "",
      "priceTotal": 38.42,
      "success": true,
      "index": 16,
      "notices": []
    },
    {
      "name": "Kuřecí prsa 500g",
      "pricePerUnit": 82.04,
      "quantity": 3.0,
      "itemCategory": "Meat",
      "quantityUnit": "ks",
      "subTotal": null,
      "tax": 42.72,
      "taxPercentage": 21.0,
      "priceIncludingTax": 246.12,
      "discount": null,
      "discountDescriptive": "",
      "priceTotal": 246.12,
      "success": true,
      "index": 17,
      "notices": []
    },
    {
      "name": "Ricotta 250g",
      "pricePerUnit": 51.47,
      "quantity": null,
      "itemCategory": "",
      "quantityUnit": "ks",
      "subTotal": 46.79,
      "tax": 4.68,
      "taxPercentage": 10.0,
      "priceIncludingTax": 51.47,
      "discount": null,
      "discountDescriptive": "",
      "priceTotal": 51.47,
      "success": true,
      "index": 18,
      "notices": []
    }
  ],
  "notices": [
    {
      "type": "TOTAL_AMOUNT_CONFLICT",
      "status": "NEW"
    }
  ],
  "_metrics": {
    "cer": 2.996,
    "f1_items": 96.393,
    "length_category": "mid",
    "n_items_groundtruth": 19
  }
}