{
  "receipt_id": "8b892333-9d07-4f87-b099-81e96ac1b96c",
  "moneyAmount": 1481.92,
  "amountFromDocument": 1481.92,
  "subTotal": 1299.76,
  "totalTax": 182.16,
  "priceIncludingTax": 1481.92,
  "discount": 0.0,
  "timeFromReceipt": "2024-01-10T12:55:00",
  "company": {
    "name": "Subway International B.V.",
    "companyCountryCode": "NL"
  },
  "shop": {
    "addressStreet": "Wenceslas Square",
    "addressStreetNumber": "15",
    "addressMunicipality": "Praha 1",
    "addressZip": "11000"
  },
  "currency": "CZK",
  "status": "DONE",
  "source": "ANDROID_RECEIPT_UPLOAD",
  "exchangeRate": null,
  "items": [
    {
      "name": "Coca Cola 0,5l",
      "pricePerUnit": 55.27,
      "quantity": 1.0,
      "itemCategory": "Beverages",
      "quantityUnit": "ks",
      "subTotal": 50.25,
      "tax": 5.02,
      "taxPercentage": 10.0,
      "priceIncludingTax": 55.27,
      "discount": null,
      "discountDescriptive": "",
      "priceTotal": 55.27,
      "success": true,
      "index": 0,
      "notices": []
    },
    {
      "name": "Caesar salát",
      "pricePerUnit": 137.71,
      "quantity": 3.0,
      "itemCategory": "Food and Drink",
      "quantityUnit": "ks",
      "subTotal": 359.24,
      "tax": 53.89,
      "taxPercentage": 15.0,
      "priceIncludingTax": 413.13,
      "discount": null,
      "discountDescriptive": "",
      "priceTotal": 413.13,
      "success": true,
      "index": 1,
      "notices": []
    },
    {
      "name": "Tiramisu",
      "pricePerUnit": 84.56,
      "quantity": 2.0,
      "itemCategory": "Food and Drink",
      "quantityUnit": "ks",
      "subTotal": 139.77,
      "tax": 29.35,
      "taxPercentage": 21.0,
      "priceIncludingTax": 169.12,
      "discount": null,
      "discountDescriptive": "",
      "priceTotal": 169.12,
      "success": true,
      "index": 2,
      "notices": []
    },
    {
      "name": "McChicken",
      "pricePerUnit": 79.84,
      "quantity": 1.0,
      "itemCategory": "Food and Drink",
      "quantityUnit": "ks",
      "subTotal": 65.98,
      "tax": 13.86,
      "taxPercentage": 21.0,
      "priceIncludingTax": 79.84,
      "discount": null,
      "discountDescriptive": "",
      "priceTotal": 79.84,
      "success": true,
      "index": 3,
      "notices": []
    },
    {
      "name": "Kuřecí wrap",
      "pricePerUnit": 123.27,
      "quantity": 1.0,
      "itemCategory": "",
      "quantityUnit": "ks",
      "subTotal": 112.06,
      "tax": 11.21,
      "taxPercentage": 10.0,
      "priceIncludingTax": 123.27,
      "discount": null,
      "discountDescriptive": "",
      "priceTotal": 123.27,
      "success": true,
      "index": 4,
      "notices": []
    },
    {
      "name": "Polévka dne",
      "pricePerUnit": 90.76,
      "quantity": 3.0,
      "itemCategory": "Food and Drink",
      "quantityUnit": "ks",
      "subTotal": 236.77,
      "tax": 35.51,
      "taxPercentage": 15.0,
      "priceIncludingTax": 272.28,
      "discount": null,
      "discountDescriptive": "",
      "priceTotal": 272.28,
      "success": true,
      "index": 5,
      "notices": []
    },
    {
      "name": "Latté",
      "pricePerUnit": 97.33,
      "quantity": 1.0,
      "itemCategory": "Beverages",
      "quantityUnit": "ks",
      "subTotal": 84.63,
      "tax": 12.7,
      "taxPercentage": 15.0,
      "priceIncludingTax": 97.33,
      "discount": null,
      "discountDescriptive": "",
      "priceTotal": 97.33,
      "success": true,
      "index": 6,
      "notices": []
    },
    {
      "name": "Hranolky velké",
      "pricePerUnit": 65.91,
      "quantity": 1.0,
      "itemCategory": "Food and Drink",
      "quantityUnit": "ks",
      "subTotal": 54.47,
      "tax": 11.44,
      "taxPercentage": 21.0,
      "priceIncludingTax": 65.91,
      "discount": null,
      "discountDescriptive": "",
      "priceTotal": 65.91,
      "success": true,
      "index": 7,
      "notices": []
    },
    {
      "name": "Latté",
      "pricePerUnit": 100.99,
      "quantity": 1.0,
      "itemCategory": "Beverages",
      "quantityUnit": "ks",
      "subTotal": 91.81,
      "tax": 9.18,
      "taxPercentage": 10.0,
      "priceIncludingTax": 100.99,
      "discount": null,
      "discountDescriptive": "",
      "priceTotal": 100.99,
      "success": true,
      "index": 8,
      "notices": []
    },
    {
      "name": "Espresso",
      "pricePerUnit": 52.39,
      "quantity": null,
      "itemCategory": "Beverages",
      "quantityUnit": "ks",
      "subTotal": 86.6,
      "tax": null,
      "taxPercentage": 21.0,
      "priceIncludingTax": 104.78,
      "discount": null,
      "discountDescriptive": "",
      "priceTotal": 104.78,
      "success": true,
      "index": 9,
      "notices": []
    }
  ],
  "notices": [],
  "_metrics": {
    "cer": 3.028,
    "f1_items": 98.89,
    "length_category": "short",
    "n_items_groundtruth": 10
  }
}