{
  "receipt_id": "13638128-4544-447b-9c41-a06b282fffb9",
  "moneyAmount": 371.56,
  "amountFromDocument": 371.56,
  "subTotal": 319.88,
  "totalTax": 51.68,
  "priceIncludingTax": 371.56,
  "discount": 0.0,
  "timeFromReceipt": "2024-11-05T10:26:00",
  "company": {
    "name": "Tesco Stores ČR a.s.",
    "companyCountryCode": "CZ"
  },
  "shop": {
    "addressStreet": "Havlíčkovo náměstí",
    "addressStreetNumber": "1199",
    "addressMunicipality": "Rudná",
    "addressZip": "25219"
  },
  "currency": "CZK",
  "status": "DONE",
  "source": "EMAIL",
  "exchangeRate": null,
  "items": [
    {
      "name": "Minerální voda 1,5l",
      "pricePerUnit": 13.74,
      "quantity": 3.0,
      "itemCategory": "Beverages",
      "quantityUnit": "ks",
      "subTotal": 35.84,
      "tax": 5.38,
      "taxPercentage": 15.0,
      "priceIncludingTax": 41.22,
      "discount": null,
      "discountDescriptive": "",
      "priceTotal": 41.22,
      "success": true,
      "index": 0,
      "notices": []
    },
    {
      "name": "Snickers 50g",
      "pricePerUnit": 16.01,
      "quantity": 2.0,
      "itemCategory": "Snacks",
      "quantityUnit": "ks",
      "subTotal": 27.84,
      "tax": 4.18,
      "taxPercentage": 15.0,
      "priceIncludingTax": 32.02,
      "discount": null,
      "discountDescriptive": "",
      "priceTotal": 32.02,
      "success": true,
      "index": 1,
      "notices": []
    },
    {
      "name": "Vepřová krkovice 1kg",
      "pricePerUnit": 141.86,
      "quantity": 1.0,
      "itemCategory": "Meat",
      "quantityUnit": "ks",
      "subTotal": 123.36,
      "tax": 18.5,
      "taxPercentage": 15.0,
      "priceIncludingTax": 141.86,
      "discount": null,
      "discountDescriptive": "",
      "priceTotal": 141.86,
      "success": true,
      "index": 2,
      "notices": []
    },
    {
      "name": "Čokoláda Milka 100g",
      "pricePerUnit": 28.45,
      "quantity": 2.0,
      "itemCategory": "Snacks",
      "quantityUnit": "ks",
      "subTotal": 47.02,
      "tax": 9.88,
      "taxPercentage": 21.0,
      "priceIncludingTax": 56.9,
      "discount": null,
      "discountDescriptive": "",
      "priceTotal": 56.9,
      "success": true,
      "index": 3,
      "notices": []
    },
    {
      "name": "Coca Cola 1,5l",
      "pricePerUnit": 38.1,
      "quantity": 1.0,
      "itemCategory": "Beverages",
      "quantityUnit": "ks",
      "subTotal": 31.49,
      "tax": 6.61,
      "taxPercentage": 21.0,
      "priceIncludingTax": 38.1,
      "discount": null,
      "discountDescriptive": "",
      "priceTotal": 41.38,
      "success": true,
      "index": 4,
      "notices": []
    },
    {
      "name": "Rohlik",
      "pricePerUnit": 3.3,
      "quantity": 3.0,
      "itemCategory": "Bakery",
      "quantityUnit": "ks",
      "subTotal": 8.18,
      "tax": 1.72,
      "taxPercentage": 21.0,
      "priceIncludingTax": 9.9,
      "discount": null,
      "discountDescriptive": "",
      "priceTotal": 9.9,
      "success": true,
      "index": 5,
      "notices": []
    },
    {
      "name": "Cibule žlutá 1kg",
      "pricePerUnit": 22.54,
      "quantity": 1.0,
      "itemCategory": "Vegetables",
      "quantityUnit": "ks",
      "subTotal": 20.49,
      "tax": 2.05,
      "taxPercentage": 10.0,
      "priceIncludingTax": 22.54,
      "discount": null,
      "discountDescriptive": "",
      "priceTotal": 22.54,
      "success": true,
      "index": 6,
      "notices": []
    },
    {
      "name": "Těstoviny penne 500g",
      "pricePerUnit": 25.74,
      "quantity": 1.0,
      "itemCategory": "Food and Drink",
      "quantityUnit": "ks",
      "subTotal": 22.38,
      "tax": 3.36,
      "taxPercentage": 15.0,
      "priceIncludingTax": 25.74,
      "discount": null,
      "discountDescriptive": "",
      "priceTotal": 25.74,
      "success": true,
      "index": 7,
      "notices": []
    }
  ],
  "notices": [
    {
      "type": "TOTAL_AMOUNT_CONFLICT",
      "status": "NEW"
    }
  ],
  "_metrics": {
    "cer": 1.611,
    "f1_items": 92.978,
    "length_category": "short",
    "n_items_groundtruth": 8
  }
}