{
  "receipt_id": "7526b1e2-c4b7-42ac-ab9e-3de468105ecf",
  "moneyAmount": 4878.72,
  "amountFromDocument": 4878.72,
  "subTotal": 4313.81,
  "totalTax": 564.91,
  "priceIncludingTax": 4878.72,
  "discount": 0.0,
  "timeFromReceipt": "2024-12-25T19:55:00",
  "company": {
    "name": "McDonald's ČR spol. s r.o.",
    "companyCountryCode": "CZ"
  },
  "shop": {
    "addressStreet": "Argentinská",
    "addressStreetNumber": "38",
    "addressMunicipality": "Praha 7",
    "addressZip": "17000"
  },
  "currency": "CZK",
  "status": "DONE",
  "source": "ANDROID_RECEIPT_UPLOAD",
  "exchangeRate": null,
  "items": [
    {
      "name": "Big Mac menu",
      "pricePerUnit": 187.68,
      "quantity": 1.0,
      "itemCategory": "Food and Drink",
      "quantityUnit": "ks",
      "subTotal": 163.2,
      "tax": 24.48,
      "taxPercentage": 15.0,
      "priceIncludingTax": 187.68,
      "discount": null,
      "discountDescriptive": "",
      "priceTotal": 187.68,
      "success": true,
      "index": 0,
      "notices": []
    },
    {
      "name": "Big Mac menu",
      "pricePerUnit": 153.56,
      "quantity": 1.0,
      "itemCategory": "Food and Drink",
      "quantityUnit": "ks",
      "subTotal": 133.53,
      "tax": null,
      "taxPercentage": 15.0,
      "priceIncludingTax": 153.56,
      "discount": null,
      "discountDescriptive": "",
      "priceTotal": 151.43,
      "success": true,
      "index": 2,
      "notices": []
    },
    {
      "name": "Caesar salát",
      "pricePerUnit": 146.9,
      "quantity": null,
      "itemCategory": "",
      "quantityUnit": "ks",
      "subTotal": 133.55,
      "tax": 13.35,
      "taxPercentage": 10.0,
      "priceIncludingTax": 146.9,
      "discount": null,
      "discountDescriptive": "",
      "priceTotal": 134.83,
      "success": true,
      "index": 3,
      "notices": []
    },
    {
      "name": "Poolévka dne",
      "pricePerUnit": 78.1,
      "quantity": 1.0,
      "itemCategory": "Food and Drink",
      "quantityUnit": "ks",
      "subTotal": 67.91,
      "tax": 10.19,
      "taxPercentage": 15.0,
      "priceIncludingTax": 78.1,
      "discount": null,
      "discountDescriptive": "",
      "priceTotal": 78.1,
      "success": true,
      "index": 4,
      "notices": []
    },
    {
      "name": "Tiramisu",
      "pricePerUnit": 77.78,
      "quantity": null,
      "itemCategory": "Food and Drink",
      "quantityUnit": "ks",
      "subTotal": 67.63,
      "tax": 10.15,
      "taxPercentage": 15.0,
      "priceIncludingTax": 77.78,
      "discount": null,
      "discountDescriptive": "",
      "priceTotal": 76.92,
      "success": true,
      "index": 5,
      "notices": []
    },
    {
      "name": "Cheesecacke",
      "pricePerUnit": 91.04,
      "quantity": null,
      "itemCategory": "Food and Drink",
      "quantityUnit": "ks",
      "subTotal": 237.5,
      "tax": 35.62,
      "taxPercentage": 15.0,
      "priceIncludingTax": 273.12,
      "discount": null,
      "discountDescriptive": "",
      "priceTotal": 273.12,
      "success": true,
      "index": 6,
      "notices": []
    },
    {
      "name": "Coleslaw",
      "pricePerUnit": 38.91,
      "quantity": 1.0,
      "itemCategory": "",
      "quantityUnit": "ks",
      "subTotal": 33.83,
      "tax": 5.08,
      "taxPercentage": 15.0,
      "priceIncludingTax": 38.91,
      "discount": null,
      "discountDescriptive": "",
      "priceTotal": 38.91,
      "success": false,
      "index": 7,
      "notices": []
    },
    {
      "name": "Espreszo",
      "pricePerUnit": 49.64,
      "quantity": 1.0,
      "itemCategory": "Beverages",
      "quantityUnit": "ks",
      "subTotal": 45.13,
      "tax": 4.51,
      "taxPercentage": 10.0,
      "priceIncludingTax": 49.64,
      "discount": null,
      "discountDescriptive": "",
      "priceTotal": 49.64,
      "success": true,
      "index": 8,
      "notices": []
    },
    {
      "name": "Espresso",
      "pricePerUnit": 47.04,
      "quantity": 2.0,
      "itemCategory": "Beverages",
      "quantityUnit": "ks",
      "subTotal": 85.53,
      "tax": 8.55,
      "taxPercentage": 10.0,
      "priceIncludingTax": 94.08,
      "discount": null,
      "discountDescriptive": "",
      "priceTotal": 94.08,
      "success": true,
      "index": 9,
      "notices": []
    },
    {
      "name": "Croissant máslo",
      "pricePerUnit": 52.61,
      "quantity": 2.0,
      "itemCategory": "Bakery",
      "quantityUnit": "ks",
      "subTotal": 86.96,
      "tax": 18.26,
      "taxPercentage": 21.0,
      "priceIncludingTax": 105.22,
      "discount": null,
      "discountDescriptive": "",
      "priceTotal": 105.22,
      "success": true,
      "index": 11,
      "notices": []
    },
    {
      "name": "Caesar salát",
      "pricePerUnit": 145.85,
      "quantity": 1.0,
      "itemCategory": "",
      "quantityUnit": "ks",
      "subTotal": null,
      "tax": 19.02,
      "taxPercentage": 15.0,
      "priceIncludingTax": 145.85,
      "discount": null,
      "discountDescriptive": "",
      "priceTotal": 148.44,
      "success": true,
      "index": 12,
      "notices": []
    },
    {
      "name": "Coleslaw",
      "pricePerUnit": 33.21,
      "quantity": 1.0,
      "itemCategory": "Food and Drink",
      "quantityUnit": "ks",
      "subTotal": 27.45,
      "tax": 5.76,
      "taxPercentage": 21.0,
      "priceIncludingTax": 33.21,
      "discount": null,
      "discountDescriptive": "",
      "priceTotal": 33.21,
      "success": true,
      "index": 14,
      "notices": []
    },
    {
      "name": "Kuřecí wrp",
      "pricePerUnit": 125.23,
      "quantity": 2.0,
      "itemCategory": "",
      "quantityUnit": "ks",
      "subTotal": 217.79,
      "tax": 32.67,
      "taxPercentage": 15.0,
      "priceIncludingTax": 250.46,
      "discount": null,
      "discountDescriptive": "",
      "priceTotal": 250.46,
      "success": true,
      "index": 16,
      "notices": []
    },
    {
      "name": "Sub 30cm Italy BMT",
      "pricePerUnit": 197.17,
      "quantity": 2.0,
      "itemCategory": "Food and Drink",
      "quantityUnit": "ks",
      "subTotal": 342.9,
      "tax": 51.44,
      "taxPercentage": 15.0,
      "priceIncludingTax": 394.34,
      "discount": null,
      "discountDescriptive": "",
      "priceTotal": 394.34,
      "success": true,
      "index": 17,
      "notices": []
    },
    {
      "name": "oca Cola 0,5l",
      "pricePerUnit": 50.25,
      "quantity": null,
      "itemCategory": "Beverages",
      "quantityUnit": "ks",
      "subTotal": 137.05,
      "tax": 13.7,
      "taxPercentage": 10.0,
      "priceIncludingTax": 150.75,
      "discount": null,
      "discountDescriptive": "",
      "priceTotal": 150.75,
      "success": true,
      "index": 19,
      "notices": []
    },
    {
      "name": "Hranolkyveloké",
      "pricePerUnit": 50.72,
      "quantity": 1.0,
      "itemCategory": "Food and Drink",
      "quantityUnit": "ks",
      "subTotal": null,
      "tax": 6.62,
      "taxPercentage": 15.0,
      "priceIncludingTax": 50.72,
      "discount": null,
      "discountDescriptive": "",
      "priceTotal": 50.72,
      "success": true,
      "index": 21,
      "notices": []
    },
    {
      "name": "Espresso",
      "pricePerUnit": 62.67,
      "quantity": null,
      "itemCategory": "",
      "quantityUnit": "ks",
      "subTotal": null,
      "tax": 17.09,
      "taxPercentage": 10.0,
      "priceIncludingTax": 188.01,
      "discount": null,
      "discountDescriptive": "",
      "priceTotal": 188.01,
      "success": false,
      "index": 23,
      "notices": []
    },
    {
      "name": "Bign Mac menu",
      "pricePerUnit": 181.93,
      "quantity": 1.0,
      "itemCategory": "Food and Drink",
      "quantityUnit": "ks",
      "subTotal": 165.39,
      "tax": 16.54,
      "taxPercentage": 10.0,
      "priceIncludingTax": 181.93,
      "discount": null,
      "discountDescriptive": "",
      "priceTotal": 181.93,
      "success": true,
      "index": 24,
      "notices": []
    },
    {
      "name": "Big Mec menu",
      "pricePerUnit": 167.35,
      "quantity": 1.0,
      "itemCategory": "Food and Drink",
      "quantityUnit": "ks",
      "subTotal": null,
      "tax": 15.21,
      "taxPercentage": 10.0,
      "priceIncludingTax": 167.35,
      "discount": null,
      "discountDescriptive": "",
      "priceTotal": 159.13,
      "success": false,
      "index": 26,
      "notices": []
    },
    {
      "name": "Colesla",
      "pricePerUnit": 35.91,
      "quantity": 3.0,
      "itemCategory": "Food and Drink",
      "quantityUnit": "ks",
      "subTotal": null,
      "tax": 9.79,
      "taxPercentage": 10.0,
      "priceIncludingTax": 107.73,
      "discount": null,
      "discountDescriptive": "",
      "priceTotal": 99.05,
      "success": false,
      "index": 28,
      "notices": []
    },
    {
      "name": "McChick3n",
      "pricePerUnit": 97.56,
      "quantity": null,
      "itemCategory": "Food and Drink",
      "quantityUnit": "ks",
      "subTotal": 241.88,
      "tax": 50.8,
      "taxPercentage": 21.0,
      "priceIncludingTax": 292.68,
      "discount": null,
      "discountDescriptive": "",
      "priceTotal": 292.68,
      "success": true,
      "index": 29,
      "notices": []
    },
    {
      "name": "Coca Coa 0a,5l",
      "pricePerUnit": 54.26,
      "quantity": 1.0,
      "itemCategory": "",
      "quantityUnit": "ks",
      "subTotal": 44.84,
      "tax": 9.42,
      "taxPercentage": 21.0,
      "priceIncludingTax": 54.26,
      "discount": null,
      "discountDescriptive": "",
      "priceTotal": 51.78,
      "success": true,
      "index": 30,
      "notices": []
    },
    {
      "name": "Espreso",
      "pricePerUnit": 59.69,
      "quantity": 1.0,
      "itemCategory": "Beverages",
      "quantityUnit": "ks",
      "subTotal": 51.9,
      "tax": 7.79,
      "taxPercentage": 15.0,
      "priceIncludingTax": 59.69,
      "discount": null,
      "discountDescriptive": "",
      "priceTotal": 59.69,
      "success": true,
      "index": 33,
      "notices": []
    },
    {
      "name": "Coca Cola 0,5l",
      "pricePerUnit": 50.63,
      "quantity": 3.0,
      "itemCategory": "Beverages",
      "quantityUnit": "ks",
      "subTotal": 138.08,
      "tax": null,
      "taxPercentage": 10.0,
      "priceIncludingTax": 151.89,
      "discount": null,
      "discountDescriptive": "",
      "priceTotal": 151.89,
      "success": true,
      "index": 34,
      "notices": []
    },
    {
      "name": "Kulřecí wrap",
      "pricePerUnit": 141.78,
      "quantity": 2.0,
      "itemCategory": "Food and Drink",
      "quantityUnit": "ks",
      "subTotal": 246.57,
      "tax": 36.99,
      "taxPercentage": 15.0,
      "priceIncludingTax": 283.56,
      "discount": null,
      "discountDescriptive": "",
      "priceTotal": 294.19,
      "success": true,
      "index": 36,
      "notices": []
    },
    {
      "name": "TiramiSu",
      "pricePerUnit": 96.56,
      "quantity": 3.0,
      "itemCategory": "Food and Drink",
      "quantityUnit": "ks",
      "subTotal": 251.9,
      "tax": 37.78,
      "taxPercentage": 15.0,
      "priceIncludingTax": 289.68,
      "discount": null,
      "discountDescriptive": "",
      "priceTotal": 295.24,
      "success": true,
      "index": 37,
      "notices": []
    },
    {
      "name": "Latté",
      "pricePerUnit": 92.71,
      "quantity": 1.0,
      "itemCategory": "",
      "quantityUnit": "ks",
      "subTotal": 84.28,
      "tax": 8.43,
      "taxPercentage": 10.0,
      "priceIncludingTax": 92.71,
      "discount": null,
      "discountDescriptive": "",
      "priceTotal": 94.18,
      "success": false,
      "index": 38,
      "notices": []
    },
    {
      "name": "Espresso",
      "pricePerUnit": 54.39,
      "quantity": 2.0,
      "itemCategory": "",
      "quantityUnit": "ks",
      "subTotal": 89.9,
      "tax": 18.88,
      "taxPercentage": 21.0,
      "priceIncludingTax": 108.78,
      "discount": null,
      "discountDescriptive": "",
      "priceTotal": 108.78,
      "success": true,
      "index": 39,
      "notices": []
    },
    {
      "name": "Big Mac menu",
      "pricePerUnit": 149.75,
      "quantity": 2.0,
      "itemCategory": "Food and Drink",
      "quantityUnit": "ks",
      "subTotal": 260.43,
      "tax": 39.07,
      "taxPercentage": 15.0,
      "priceIncludingTax": 299.5,
      "discount": null,
      "discountDescriptive": "",
      "priceTotal": 323.64,
      "success": true,
      "index": 40,
      "notices": []
    },
    {
      "name": "Big Mc menu",
      "pricePerUnit": 174.22,
      "quantity": 1.0,
      "itemCategory": "Food and Drink",
      "quantityUnit": "ks",
      "subTotal": 158.38,
      "tax": 15.84,
      "taxPercentage": 10.0,
      "priceIncludingTax": 174.22,
      "discount": null,
      "discountDescriptive": "",
      "priceTotal": 174.22,
      "success": true,
      "index": 41,
      "notices": []
    },
    {
      "name": "McChicken",
      "pricePerUnit": 90.9,
      "quantity": 1.0,
      "itemCategory": "Food and Drink",
      "quantityUnit": "ks",
      "subTotal": 82.64,
      "tax": 8.26,
      "taxPercentage": 10.0,
      "priceIncludingTax": 90.9,
      "discount": null,
      "discountDescriptive": "",
      "priceTotal": 84.19,
      "success": true,
      "index": 45,
      "notices": []
    },
    {
      "name": "Cheescake",
      "pricePerUnit": 104.43,
      "quantity": 1.0,
      "itemCategory": "",
      "quantityUnit": "ks",
      "subTotal": 90.81,
      "tax": 13.62,
      "taxPercentage": 15.0,
      "priceIncludingTax": 104.43,
      "discount": null,
      "discountDescriptive": "",
      "priceTotal": 102.27,
      "success": true,
      "index": 46,
      "notices": []
    }
  ],
  "notices": [
    {
      "type": "TOTAL_AMOUNT_CONFLICT",
      "status": "NEW"
    }
  ],
  "_metrics": {
    "cer": 10.978,
    "f1_items": 61.363,
    "length_category": "long",
    "n_items_groundtruth": 47
  }
}