{
  "receipt_id": "b098a2db-6585-4ced-821f-7c6636017076",
  "moneyAmount": 5124.07,
  "amountFromDocument": 5124.07,
  "subTotal": 4512.47,
  "totalTax": 611.6,
  "priceIncludingTax": 5124.07,
  "discount": 0.0,
  "timeFromReceipt": "2024-06-14T19:16:00",
  "company": {
    "name": "ROSSMANN, spol. s r.o.",
    "companyCountryCode": "CZ"
  },
  "shop": {
    "addressStreet": "Nádražní",
    "addressStreetNumber": "762/32",
    "addressMunicipality": "Praha 5",
    "addressZip": "15000"
  },
  "currency": "CZK",
  "status": "DONE",
  "source": "ANDROID_RECEIPT_UPLOAD",
  "exchangeRate": null,
  "items": [
    {
      "name": "Náplasti Hartmann 20ks",
      "pricePerUnit": 53.08,
      "quantity": 2.0,
      "itemCategory": "Pharmacy",
      "quantityUnit": "ks",
      "subTotal": 96.51,
      "tax": 9.65,
      "taxPercentage": 10.0,
      "priceIncludingTax": 106.16,
      "discount": null,
      "discountDescriptive": "",
      "priceTotal": 106.16,
      "success": true,
      "index": 0,
      "notices": []
    },
    {
      "name": "Pleny Pampers 44ks",
      "pricePerUnit": 339.93,
      "quantity": 3.0,
      "itemCategory": "Baby Products",
      "quantityUnit": "ks",
      "subTotal": 927.08,
      "tax": 92.71,
      "taxPercentage": 10.0,
      "priceIncludingTax": 1019.79,
      "discount": null,
      "discountDescriptive": "",
      "priceTotal": 1019.79,
      "success": true,
      "index": 1,
      "notices": []
    },
    {
      "name": "Dětský šampon 250ml",
      "pricePerUnit": 90.05,
      "quantity": 3.0,
      "itemCategory": "Baby Products",
      "quantityUnit": "ks",
      "subTotal": null,
      "tax": 46.89,
      "taxPercentage": 21.0,
      "priceIncludingTax": 270.15,
      "discount": null,
      "discountDescriptive": "",
      "priceTotal": 270.15,
      "success": true,
      "index": 2,
      "notices": []
    },
    {
      "name": "Deodorant Rexona 150ml",
      "pricePerUnit": 78.54,
      "quantity": 1.0,
      "itemCategory": "",
      "quantityUnit": "ks",
      "subTotal": 64.91,
      "tax": 13.63,
      "taxPercentage": 21.0,
      "priceIncludingTax": 78.54,
      "discount": null,
      "discountDescriptive": "",
      "priceTotal": 78.54,
      "success": true,
      "index": 3,
      "notices": []
    },
    {
      "name": "Ibalgin 400mg 24tbl",
      "pricePerUnit": 77.03,
      "quantity": 1.0,
      "itemCategory": "Pharmacy",
      "quantityUnit": "ks",
      "subTotal": 70.03,
      "tax": 7.0,
      "taxPercentage": 10.0,
      "priceIncludingTax": 77.03,
      "discount": null,
      "discountDescriptive": "",
      "priceTotal": 71.28,
      "success": true,
      "index": 4,
      "notices": []
    },
    {
      "name": "Kondicionér Dove 200ml",
      "pricePerUnit": 73.78,
      "quantity": 2.0,
      "itemCategory": "Cosmetics",
      "quantityUnit": "ks",
      "subTotal": 134.15,
      "tax": 13.41,
      "taxPercentage": 10.0,
      "priceIncludingTax": 147.56,
      "discount": null,
      "discountDescriptive": "",
      "priceTotal": 147.56,
      "success": true,
      "index": 5,
      "notices": []
    },
    {
      "name": "Make-up základ 30ml",
      "pricePerUnit": 178.97,
      "quantity": 3.0,
      "itemCategory": "Cosmetics",
      "quantityUnit": "ks",
      "subTotal": 466.88,
      "tax": 70.03,
      "taxPercentage": 15.0,
      "priceIncludingTax": 536.91,
      "discount": null,
      "discountDescriptive": "",
      "priceTotal": 536.91,
      "success": true,
      "index": 6,
      "notices": []
    },
    {
      "name": "Rtěnka",
      "pricePerUnit": 158.05,
      "quantity": 1.0,
      "itemCategory": "Cosmetics",
      "quantityUnit": "ks",
      "subTotal": 143.68,
      "tax": 14.37,
      "taxPercentage": 10.0,
      "priceIncludingTax": 158.05,
      "discount": null,
      "discountDescriptive": "",
      "priceTotal": 158.05,
      "success": true,
      "index": 7,
      "notices": []
    },
    {
      "name": "Vitamín C 500mg 60tbl",
      "pricePerUnit": 146.88,
      "quantity": 3.0,
      "itemCategory": "Pharmacy",
      "quantityUnit": "ks",
      "subTotal": 400.58,
      "tax": 40.06,
      "taxPercentage": 10.0,
      "priceIncludingTax": 440.64,
      "discount": null,
      "discountDescriptive": "",
      "priceTotal": 440.64,
      "success": true,
      "index": 8,
      "notices": []
    },
    {
      "name": "Rukavice klatex M 100ks",
      "pricePerUnit": 155.84,
      "quantity": 1.0,
      "itemCategory": "Household Supplies",
      "quantityUnit": "ks",
      "subTotal": 128.79,
      "tax": 27.05,
      "taxPercentage": 21.0,
      "priceIncludingTax": 155.84,
      "discount": null,
      "discountDescriptive": "",
      "priceTotal": 155.84,
      "success": false,
      "index": 9,
      "notices": []
    },
    {
      "name": "Make-up základ 30ml",
      "pricePerUnit": 175.21,
      "quantity": 3.0,
      "itemCategory": "",
      "quantityUnit": "ks",
      "subTotal": 477.85,
      "tax": 47.78,
      "taxPercentage": 10.0,
      "priceIncludingTax": 525.63,
      "discount": null,
      "discountDescriptive": "",
      "priceTotal": 525.63,
      "success": true,
      "index": 10,
      "notices": []
    },
    {
      "name": "Bavlněné tampony 100ks",
      "pricePerUnit": 53.69,
      "quantity": 3.0,
      "itemCategory": "Personal Care",
      "quantityUnit": "ks",
      "subTotal": 133.12,
      "tax": 27.95,
      "taxPercentage": 21.0,
      "priceIncludingTax": 161.07,
      "discount": null,
      "discountDescriptive": "",
      "priceTotal": 161.07,
      "success": true,
      "index": 11,
      "notices": []
    },
    {
      "name": "Dětský šampon 250ml",
      "pricePerUnit": 97.7,
      "quantity": 3.0,
      "itemCategory": "Baby Products",
      "quantityUnit": "ks",
      "subTotal": 242.23,
      "tax": 50.87,
      "taxPercentage": 21.0,
      "priceIncludingTax": 293.1,
      "discount": null,
      "discountDescriptive": "",
      "priceTotal": 293.1,
      "success": true,
      "index": 12,
      "notices": []
    },
    {
      "name": "Kondicionér Dove 200ml",
      "pricePerUnit": 67.53,
      "quantity": 1.0,
      "itemCategory": "Cosmetics",
      "quantityUnit": "ks",
      "subTotal": 55.81,
      "tax": 11.72,
      "taxPercentage": 21.0,
      "priceIncludingTax": 67.53,
      "discount": null,
      "discountDescriptive": "",
      "priceTotal": 67.53,
      "success": true,
      "index": 13,
      "notices": []
    },
    {
      "name": "Ibalgin 400mg 24tbl",
      "pricePerUnit": 97.1,
      "quantity": 1.0,
      "itemCategory": "Pharmacy",
      "quantityUnit": "ks",
      "subTotal": 80.25,
      "tax": 16.85,
      "taxPercentage": 21.0,
      "priceIncludingTax": 97.1,
      "discount": null,
      "discountDescriptive": "",
      "priceTotal": 97.1,
      "success": true,
      "index": 14,
      "notices": []
    },
    {
      "name": "Deodorant Rexona 150ml",
      "pricePerUnit": 87.75,
      "quantity": 1.0,
      "itemCategory": "Personal Care",
      "quantityUnit": "ks",
      "subTotal": 76.3,
      "tax": 11.45,
      "taxPercentage": 15.0,
      "priceIncludingTax": 87.75,
      "discount": null,
      "discountDescriptive": "",
      "priceTotal": 87.75,
      "success": true,
      "index": 15,
      "notices": []
    },
    {
      "name": "Náplasti Hartmann 20ks",
      "pricePerUnit": 48.22,
      "quantity": 3.0,
      "itemCategory": "Pharmacy",
      "quantityUnit": "ks",
      "subTotal": 131.51,
      "tax": 13.15,
      "taxPercentage": 10.0,
      "priceIncludingTax": 144.66,
      "discount": null,
      "discountDescriptive": "",
      "priceTotal": 144.66,
      "success": true,
      "index": 16,
      "notices": []
    },
    {
      "name": "Ibalgin 400mg 24tbl",
      "pricePerUnit": 99.96,
      "quantity": 1.0,
      "itemCategory": "Pharmacy",
      "quantityUnit": "ks",
      "subTotal": 86.92,
      "tax": 13.04,
      "taxPercentage": 15.0,
      "priceIncludingTax": 99.96,
      "discount": null,
      "discountDescriptive": "",
      "priceTotal": 99.96,
      "success": true,
      "index": 17,
      "notices": []
    },
    {
      "name": "Deodorant nexona 150ml",
      "pricePerUnit": 81.96,
      "quantity": 1.0,
      "itemCategory": "Personal Care",
      "quantityUnit": "ks",
      "subTotal": 71.27,
      "tax": 10.69,
      "taxPercentage": 15.0,
      "priceIncludingTax": 81.96,
      "discount": null,
      "discountDescriptive": "",
      "priceTotal": 81.96,
      "success": true,
      "index": 18,
      "notices": []
    },
    {
      "name": "Vitamín C 500mg 60tbl",
      "pricePerUnit": 140.79,
      "quantity": 3.0,
      "itemCategory": "Pharmacy",
      "quantityUnit": "ks",
      "subTotal": 349.07,
      "tax": 73.3,
      "taxPercentage": 21.0,
      "priceIncludingTax": 422.37,
      "discount": null,
      "discountDescriptive": "",
      "priceTotal": 446.68,
      "success": false,
      "index": 19,
      "notices": []
    },
    {
      "name": "Náplasti Hartmann 20ks",
      "pricePerUnit": 44.57,
      "quantity": 3.0,
      "itemCategory": "Pharmacy",
      "quantityUnit": "ks",
      "subTotal": 110.5,
      "tax": null,
      "taxPercentage": 21.0,
      "priceIncludingTax": 133.71,
      "discount": null,
      "discountDescriptive": "",
      "priceTotal": 133.71,
      "success": true,
      "index": 20,
      "notices": []
    }
  ],
  "notices": [
    {
      "type": "TOTAL_AMOUNT_CONFLICT",
      "status": "NEW"
    }
  ],
  "_metrics": {
    "cer": 9.351,
    "f1_items": 81.387,
    "length_category": "mid",
    "n_items_groundtruth": 21
  }
}