{
  "receipt_id": "55c8feda-a1a3-4293-9d62-37e9d70f610c",
  "moneyAmount": 982.99,
  "amountFromDocument": 982.99,
  "subTotal": 860.7,
  "totalTax": 122.29,
  "priceIncludingTax": 982.99,
  "discount": 0.0,
  "timeFromReceipt": "2025-04-26T09:01:00",
  "company": {
    "name": "Lidl Česká republika v.o.s.",
    "companyCountryCode": "CZ"
  },
  "shop": {
    "addressStreet": "Budějovická",
    "addressStreetNumber": "1667/64",
    "addressMunicipality": "Praha 4",
    "addressZip": "14000"
  },
  "currency": "CZK",
  "status": "DONE",
  "source": "ANDROID_RECEIPT_UPLOAD",
  "exchangeRate": null,
  "items": [
    {
      "name": "Bageta",
      "pricePerUnit": 17.17,
      "quantity": 1.0,
      "itemCategory": "Bakery",
      "quantityUnit": "ks",
      "subTotal": 14.93,
      "tax": 2.24,
      "taxPercentage": 15.0,
      "priceIncludingTax": 17.17,
      "discount": null,
      "discountDescriptive": "",
      "priceTotal": 17.17,
      "success": true,
      "index": 0,
      "notices": []
    },
    {
      "name": "Rohlík sezamový",
      "pricePerUnit": 3.55,
      "quantity": 1.0,
      "itemCategory": "Bakery",
      "quantityUnit": "ks",
      "subTotal": 2.93,
      "tax": null,
      "taxPercentage": 21.0,
      "priceIncludingTax": 3.55,
      "discount": null,
      "discountDescriptive": "",
      "priceTotal": 3.55,
      "success": true,
      "index": 1,
      "notices": []
    },
    {
      "name": "Jablka Golden 2kg",
      "pricePerUnit": 60.87,
      "quantity": 1.0,
      "itemCategory": "Fresh Products",
      "quantityUnit": "ks",
      "subTotal": 55.34,
      "tax": 5.53,
      "taxPercentage": 10.0,
      "priceIncludingTax": 60.87,
      "discount": null,
      "discountDescriptive": "",
      "priceTotal": 60.87,
      "success": true,
      "index": 2,
      "notices": []
    },
    {
      "name": "Cottage sýr 180g",
      "pricePerUnit": 31.03,
      "quantity": 1.0,
      "itemCategory": "",
      "quantityUnit": "ks",
      "subTotal": 26.98,
      "tax": 4.05,
      "taxPercentage": 15.0,
      "priceIncludingTax": 31.03,
      "discount": null,
      "discountDescriptive": "",
      "priceTotal": 31.03,
      "success": true,
      "index": 3,
      "notices": []
    },
    {
      "name": "Müsli tyčinka",
      "pricePerUnit": 14.35,
      "quantity": 3.0,
      "itemCategory": "Snacks",
      "quantityUnit": "ks",
      "subTotal": 35.58,
      "tax": 7.47,
      "taxPercentage": 21.0,
      "priceIncludingTax": 43.05,
      "discount": null,
      "discountDescriptive": "",
      "priceTotal": 43.05,
      "success": true,
      "index": 4,
      "notices": []
    },
    {
      "name": "Džus pomeranč 1l",
      "pricePerUnit": 42.08,
      "quantity": 2.0,
      "itemCategory": "Beverages",
      "quantityUnit": "ks",
      "subTotal": 73.18,
      "tax": 10.98,
      "taxPercentage": 15.0,
      "priceIncludingTax": 84.16,
      "discount": null,
      "discountDescriptive": "",
      "priceTotal": 84.16,
      "success": true,
      "index": 5,
      "notices": []
    },
    {
      "name": "Jogurt bílý 150g",
      "pricePerUnit": 9.19,
      "quantity": 1.0,
      "itemCategory": "Dairy Products",
      "quantityUnit": "ks",
      "subTotal": 7.6,
      "tax": 1.59,
      "taxPercentage": 21.0,
      "priceIncludingTax": 9.19,
      "discount": null,
      "discountDescriptive": "",
      "priceTotal": 9.19,
      "success": true,
      "index": 6,
      "notices": []
    },
    {
      "name": "Okurka salátová 1ks",
      "pricePerUnit": 11.9,
      "quantity": 2.0,
      "itemCategory": "Vegetables",
      "quantityUnit": "ks",
      "subTotal": 19.67,
      "tax": 4.13,
      "taxPercentage": 21.0,
      "priceIncludingTax": 23.8,
      "discount": null,
      "discountDescriptive": "",
      "priceTotal": 23.8,
      "success": true,
      "index": 7,
      "notices": []
    },
    {
      "name": "Coca Cola 1,5l",
      "pricePerUnit": 33.31,
      "quantity": 3.0,
      "itemCategory": "Beverages",
      "quantityUnit": "ks",
      "subTotal": 90.85,
      "tax": 9.08,
      "taxPercentage": 10.0,
      "priceIncludingTax": 99.93,
      "discount": null,
      "discountDescriptive": "",
      "priceTotal": 99.93,
      "success": true,
      "index": 8,
      "notices": []
    },
    {
      "name": "Jogurt bílý 150g",
      "pricePerUnit": 10.02,
      "quantity": 1.0,
      "itemCategory": "Dairy Products",
      "quantityUnit": "ks",
      "subTotal": 8.28,
      "tax": 1.74,
      "taxPercentage": 21.0,
      "priceIncludingTax": 10.02,
      "discount": null,
      "discountDescriptive": "",
      "priceTotal": 10.02,
      "success": true,
      "index": 9,
      "notices": []
    },
    {
      "name": "Müslityčinka",
      "pricePerUnit": 12.49,
      "quantity": 3.0,
      "itemCategory": "Snacks",
      "quantityUnit": "ks",
      "subTotal": 34.06,
      "tax": 3.41,
      "taxPercentage": 10.0,
      "priceIncludingTax": 37.47,
      "discount": null,
      "discountDescriptive": "",
      "priceTotal": 37.47,
      "success": true,
      "index": 10,
      "notices": []
    },
    {
      "name": "Jar prostředek 500ml",
      "pricePerUnit": 38.74,
      "quantity": 2.0,
      "itemCategory": "Household Supplies",
      "quantityUnit": "ks",
      "subTotal": 70.44,
      "tax": 7.04,
      "taxPercentage": 10.0,
      "priceIncludingTax": 77.48,
      "discount": null,
      "discountDescriptive": "",
      "priceTotal": 77.48,
      "success": true,
      "index": 11,
      "notices": []
    },
    {
      "name": "Bageta",
      "pricePerUnit": 22.11,
      "quantity": 1.0,
      "itemCategory": "Bakery",
      "quantityUnit": "ks",
      "subTotal": 19.23,
      "tax": 2.88,
      "taxPercentage": 15.0,
      "priceIncludingTax": 22.11,
      "discount": null,
      "discountDescriptive": "",
      "priceTotal": 22.11,
      "success": true,
      "index": 12,
      "notices": []
    },
    {
      "name": "Rýže dlouhozrnná 1kg",
      "pricePerUnit": 28.33,
      "quantity": 3.0,
      "itemCategory": "Food and Drink",
      "quantityUnit": "ks",
      "subTotal": 70.24,
      "tax": 14.75,
      "taxPercentage": 21.0,
      "priceIncludingTax": 84.99,
      "discount": null,
      "discountDescriptive": "",
      "priceTotal": 84.99,
      "success": true,
      "index": 13,
      "notices": []
    },
    {
      "name": "Rýže dlouhozrnná 1kg",
      "pricePerUnit": 26.29,
      "quantity": 1.0,
      "itemCategory": "Food and Drink",
      "quantityUnit": "ks",
      "subTotal": 21.73,
      "tax": 4.56,
      "taxPercentage": 21.0,
      "priceIncludingTax": 26.29,
      "discount": null,
      "discountDescriptive": "",
      "priceTotal": 26.29,
      "success": true,
      "index": 14,
      "notices": []
    },
    {
      "name": "Ricotta 250g",
      "pricePerUnit": 47.99,
      "quantity": 1.0,
      "itemCategory": "",
      "quantityUnit": "ks",
      "subTotal": 41.73,
      "tax": 6.26,
      "taxPercentage": 15.0,
      "priceIncludingTax": 47.99,
      "discount": null,
      "discountDescriptive": "",
      "priceTotal": 47.99,
      "success": true,
      "index": 15,
      "notices": []
    },
    {
      "name": "Mléko plnotučné 1l",
      "pricePerUnit": 21.65,
      "quantity": 1.0,
      "itemCategory": "Dairy Products",
      "quantityUnit": "ks",
      "subTotal": 17.89,
      "tax": 3.76,
      "taxPercentage": 21.0,
      "priceIncludingTax": 21.65,
      "discount": null,
      "discountDescriptive": "",
      "priceTotal": 21.65,
      "success": true,
      "index": 16,
      "notices": []
    },
    {
      "name": "Kečup Hamé 500g",
      "pricePerUnit": 36.66,
      "quantity": 1.0,
      "itemCategory": "Food and Drink",
      "quantityUnit": "ks",
      "subTotal": 31.88,
      "tax": 4.78,
      "taxPercentage": 15.0,
      "priceIncludingTax": 36.66,
      "discount": null,
      "discountDescriptive": "",
      "priceTotal": 36.66,
      "success": true,
      "index": 17,
      "notices": []
    },
    {
      "name": "Rohlik",
      "pricePerUnit": 3.03,
      "quantity": 3.0,
      "itemCategory": "Bakery",
      "quantityUnit": "ks",
      "subTotal": 7.51,
      "tax": 1.58,
      "taxPercentage": 21.0,
      "priceIncludingTax": 9.09,
      "discount": null,
      "discountDescriptive": "",
      "priceTotal": 9.09,
      "success": true,
      "index": 18,
      "notices": []
    },
    {
      "name": "Uzená klobása 200g",
      "pricePerUnit": 43.85,
      "quantity": 2.0,
      "itemCategory": "Meat Products",
      "quantityUnit": "ks",
      "subTotal": 76.26,
      "tax": 11.44,
      "taxPercentage": 15.0,
      "priceIncludingTax": 87.7,
      "discount": null,
      "discountDescriptive": "",
      "priceTotal": 87.7,
      "success": true,
      "index": 19,
      "notices": []
    },
    {
      "name": "Kečup Hámé 500g",
      "pricePerUnit": 37.02,
      "quantity": 3.0,
      "itemCategory": "Food and Drink",
      "quantityUnit": "ks",
      "subTotal": 100.96,
      "tax": 10.1,
      "taxPercentage": 10.0,
      "priceIncludingTax": 111.06,
      "discount": null,
      "discountDescriptive": "",
      "priceTotal": 111.06,
      "success": true,
      "index": 20,
      "notices": []
    },
    {
      "name": "Papriky červené 500g",
      "pricePerUnit": 37.73,
      "quantity": 1.0,
      "itemCategory": "Vegetables",
      "quantityUnit": "ks",
      "subTotal": 32.81,
      "tax": 4.92,
      "taxPercentage": 15.0,
      "priceIncludingTax": 37.73,
      "discount": null,
      "discountDescriptive": "",
      "priceTotal": 37.73,
      "success": true,
      "index": 21,
      "notices": []
    }
  ],
  "notices": [],
  "_metrics": {
    "cer": 3.829,
    "f1_items": 90.958,
    "length_category": "mid",
    "n_items_groundtruth": 22
  }
}