{
  "receipt_id": "4f8c5636-b6ff-40c7-893e-5860f88569ad",
  "moneyAmount": 12198.84,
  "amountFromDocument": 12198.84,
  "subTotal": 11060.68,
  "totalTax": 1138.16,
  "priceIncludingTax": 12198.84,
  "discount": 0.0,
  "timeFromReceipt": "2024-04-15T13:35:00",
  "company": {
    "name": "Orlen Unipetrol RPA s.r.o.",
    "companyCountryCode": "CZ"
  },
  "shop": {
    "addressStreet": "Náměstí Míru",
    "addressStreetNumber": "1",
    "addressMunicipality": "Praha 2",
    "addressZip": "12000"
  },
  "currency": "CZK",
  "status": "DONE",
  "source": "EMAIL",
  "exchangeRate": null,
  "items": [
    {
      "name": "Hot dog",
      "pricePerUnit": 50.43,
      "quantity": 1.0,
      "itemCategory": "Food and Drink",
      "quantityUnit": "ks",
      "subTotal": 45.85,
      "tax": 4.58,
      "taxPercentage": 10.0,
      "priceIncludingTax": 50.43,
      "discount": null,
      "discountDescriptive": "",
      "priceTotal": 50.43,
      "success": true,
      "index": 0,
      "notices": []
    },
    {
      "name": "Cappuccino",
      "pricePerUnit": 52.47,
      "quantity": 1.0,
      "itemCategory": "Beverages",
      "quantityUnit": "ks",
      "subTotal": 43.36,
      "tax": 9.11,
      "taxPercentage": 21.0,
      "priceIncludingTax": 52.47,
      "discount": null,
      "discountDescriptive": "",
      "priceTotal": 52.47,
      "success": true,
      "index": 1,
      "notices": []
    },
    {
      "name": "Red Bull 250ml",
      "pricePerUnit": 55.58,
      "quantity": 1.0,
      "itemCategory": "Beverages",
      "quantityUnit": "ks",
      "subTotal": 45.93,
      "tax": 9.65,
      "taxPercentage": 21.0,
      "priceIncludingTax": 55.58,
      "discount": null,
      "discountDescriptive": "",
      "priceTotal": 55.58,
      "success": true,
      "index": 2,
      "notices": []
    },
    {
      "name": "Diesel 28.5l",
      "pricePerUnit": 1071.43,
      "quantity": 1.0,
      "itemCategory": "Fuel",
      "quantityUnit": "ks",
      "subTotal": 974.03,
      "tax": 97.4,
      "taxPercentage": 10.0,
      "priceIncludingTax": 1071.43,
      "discount": null,
      "discountDescriptive": "",
      "priceTotal": 1071.43,
      "success": true,
      "index": 3,
      "notices": []
    },
    {
      "name": "Kapalina do ostřikovačů 1l",
      "pricePerUnit": 45.29,
      "quantity": 1.0,
      "itemCategory": "Automotive",
      "quantityUnit": "ks",
      "subTotal": 39.38,
      "tax": 5.91,
      "taxPercentage": 15.0,
      "priceIncludingTax": 45.29,
      "discount": null,
      "discountDescriptive": "",
      "priceTotal": 45.29,
      "success": true,
      "index": 4,
      "notices": []
    },
    {
      "name": "Hot dog",
      "pricePerUnit": 52.67,
      "quantity": 1.0,
      "itemCategory": "Food and Drink",
      "quantityUnit": "ks",
      "subTotal": 43.53,
      "tax": 9.14,
      "taxPercentage": 21.0,
      "priceIncludingTax": 52.67,
      "discount": null,
      "discountDescriptive": "",
      "priceTotal": 52.67,
      "success": true,
      "index": 5,
      "notices": []
    },
    {
      "name": "Natural 95 34.87l",
      "pricePerUnit": 1634.64,
      "quantity": 1.0,
      "itemCategory": "Fuel",
      "quantityUnit": "ks",
      "subTotal": 1486.04,
      "tax": 148.6,
      "taxPercentage": 10.0,
      "priceIncludingTax": 1634.64,
      "discount": null,
      "discountDescriptive": "",
      "priceTotal": 1634.64,
      "success": true,
      "index": 6,
      "notices": []
    },
    {
      "name": "Natural 95 34.87l",
      "pricePerUnit": 1502.77,
      "quantity": 1.0,
      "itemCategory": "Fuel",
      "quantityUnit": "ks",
      "subTotal": 1366.15,
      "tax": 136.62,
      "taxPercentage": 10.0,
      "priceIncludingTax": 1502.77,
      "discount": null,
      "discountDescriptive": "",
      "priceTotal": 1502.77,
      "success": true,
      "index": 7,
      "notices": []
    },
    {
      "name": "Hot dog",
      "pricePerUnit": 48.76,
      "quantity": 1.0,
      "itemCategory": "Food and Drink",
      "quantityUnit": "ks",
      "subTotal": 42.4,
      "tax": 6.36,
      "taxPercentage": 15.0,
      "priceIncludingTax": 48.76,
      "discount": null,
      "discountDescriptive": "",
      "priceTotal": 48.76,
      "success": true,
      "index": 8,
      "notices": []
    },
    {
      "name": "Sendvič šunka sýr",
      "pricePerUnit": 59.49,
      "quantity": 1.0,
      "itemCategory": "Food and Drink",
      "quantityUnit": "ks",
      "subTotal": 51.73,
      "tax": 7.76,
      "taxPercentage": 15.0,
      "priceIncludingTax": 59.49,
      "discount": null,
      "discountDescriptive": "",
      "priceTotal": 59.49,
      "success": true,
      "index": 9,
      "notices": []
    },
    {
      "name": "Kapalina do ostřikovačů 1l",
      "pricePerUnit": 45.66,
      "quantity": 1.0,
      "itemCategory": "Automotive",
      "quantityUnit": "ks",
      "subTotal": 41.51,
      "tax": 4.15,
      "taxPercentage": 10.0,
      "priceIncludingTax": 45.66,
      "discount": null,
      "discountDescriptive": "",
      "priceTotal": 45.66,
      "success": true,
      "index": 10,
      "notices": []
    },
    {
      "name": "Hot dog",
      "pricePerUnit": 43.3,
      "quantity": 1.0,
      "itemCategory": "Food and Drink",
      "quantityUnit": "ks",
      "subTotal": 37.65,
      "tax": 5.65,
      "taxPercentage": 15.0,
      "priceIncludingTax": 43.3,
      "discount": null,
      "discountDescriptive": "",
      "priceTotal": 43.3,
      "success": true,
      "index": 11,
      "notices": []
    },
    {
      "name": "Natural 95 34.87l",
      "pricePerUnit": 1581.56,
      "quantity": 1.0,
      "itemCategory": "Fuel",
      "quantityUnit": "ks",
      "subTotal": 1437.78,
      "tax": 143.78,
      "taxPercentage": 10.0,
      "priceIncludingTax": 1581.56,
      "discount": null,
      "discountDescriptive": "",
      "priceTotal": 1581.56,
      "success": true,
      "index": 12,
      "notices": []
    },
    {
      "name": "Noviny MF Dnes",
      "pricePerUnit": 23.34,
      "quantity": 1.0,
      "itemCategory": "Other",
      "quantityUnit": "ks",
      "subTotal": 21.22,
      "tax": 2.12,
      "taxPercentage": 10.0,
      "priceIncludingTax": 23.34,
      "discount": null,
      "discountDescriptive": "",
      "priceTotal": 23.34,
      "success": true,
      "index": 13,
      "notices": []
    },
    {
      "name": "Red Bull 250ml",
      "pricePerUnit": 44.7,
      "quantity": 1.0,
      "itemCategory": "Beverages",
      "quantityUnit": "ks",
      "subTotal": 38.87,
      "tax": 5.83,
      "taxPercentage": 15.0,
      "priceIncludingTax": 44.7,
      "discount": null,
      "discountDescriptive": "",
      "priceTotal": 44.7,
      "success": true,
      "index": 14,
      "notices": []
    },
    {
      "name": "Sendvič šunka sýr",
      "pricePerUnit": 65.82,
      "quantity": 1.0,
      "itemCategory": "Food and Drink",
      "quantityUnit": "ks",
      "subTotal": 57.23,
      "tax": 8.59,
      "taxPercentage": 15.0,
      "priceIncludingTax": 65.82,
      "discount": null,
      "discountDescriptive": "",
      "priceTotal": 65.82,
      "success": true,
      "index": 15,
      "notices": []
    },
    {
      "name": "Diesel 28.5l",
      "pricePerUnit": 1321.28,
      "quantity": 1.0,
      "itemCategory": "Fuel",
      "quantityUnit": "ks",
      "subTotal": 1201.16,
      "tax": 120.12,
      "taxPercentage": 10.0,
      "priceIncludingTax": 1321.28,
      "discount": null,
      "discountDescriptive": "",
      "priceTotal": 1321.28,
      "success": true,
      "index": 16,
      "notices": []
    },
    {
      "name": "Diesel 28.5l",
      "pricePerUnit": 1253.02,
      "quantity": 1.0,
      "itemCategory": "Fuel",
      "quantityUnit": "ks",
      "subTotal": 1139.11,
      "tax": 113.91,
      "taxPercentage": 10.0,
      "priceIncludingTax": 1253.02,
      "discount": null,
      "discountDescriptive": "",
      "priceTotal": 1253.02,
      "success": true,
      "index": 17,
      "notices": []
    },
    {
      "name": "Sendvič šunka sýr",
      "pricePerUnit": 61.29,
      "quantity": 1.0,
      "itemCategory": "Food and Drink",
      "quantityUnit": "ks",
      "subTotal": 55.72,
      "tax": 5.57,
      "taxPercentage": 10.0,
      "priceIncludingTax": 61.29,
      "discount": null,
      "discountDescriptive": "",
      "priceTotal": 61.29,
      "success": true,
      "index": 18,
      "notices": []
    },
    {
      "name": "Natural 95 34.87l",
      "pricePerUnit": 1473.42,
      "quantity": 1.0,
      "itemCategory": "Fuel",
      "quantityUnit": "ks",
      "subTotal": 1339.47,
      "tax": 133.95,
      "taxPercentage": 10.0,
      "priceIncludingTax": 1473.42,
      "discount": null,
      "discountDescriptive": "",
      "priceTotal": 1473.42,
      "success": true,
      "index": 19,
      "notices": []
    },
    {
      "name": "Kapalina do ostřikovačů 1l",
      "pricePerUnit": 45.09,
      "quantity": 1.0,
      "itemCategory": "Automotive",
      "quantityUnit": "ks",
      "subTotal": 37.26,
      "tax": 7.83,
      "taxPercentage": 21.0,
      "priceIncludingTax": 45.09,
      "discount": null,
      "discountDescriptive": "",
      "priceTotal": 45.09,
      "success": true,
      "index": 20,
      "notices": []
    },
    {
      "name": "Sendvič šunka sýr",
      "pricePerUnit": 79.61,
      "quantity": 1.0,
      "itemCategory": "Food and Drink",
      "quantityUnit": "ks",
      "subTotal": 72.37,
      "tax": 7.24,
      "taxPercentage": 10.0,
      "priceIncludingTax": 79.61,
      "discount": null,
      "discountDescriptive": "",
      "priceTotal": 79.61,
      "success": true,
      "index": 21,
      "notices": []
    },
    {
      "name": "Natural 95 34.87l",
      "pricePerUnit": 1587.22,
      "quantity": 1.0,
      "itemCategory": "Fuel",
      "quantityUnit": "ks",
      "subTotal": 1442.93,
      "tax": 144.29,
      "taxPercentage": 10.0,
      "priceIncludingTax": 1587.22,
      "discount": null,
      "discountDescriptive": "",
      "priceTotal": 1587.22,
      "success": true,
      "index": 22,
      "notices": []
    }
  ],
  "notices": []
}