{
  "receipt_id": "a114708a-826c-4028-8224-c44279838517",
  "moneyAmount": 290.71,
  "amountFromDocument": 290.71,
  "subTotal": 261.13,
  "totalTax": 29.58,
  "priceIncludingTax": 290.71,
  "discount": 0.0,
  "timeFromReceipt": "2024-03-14T15:17:00",
  "company": {
    "name": "BILLA, spol. s r.o.",
    "companyCountryCode": "CZ"
  },
  "shop": {
    "addressStreet": "Skandinávská",
    "addressStreetNumber": "131/1",
    "addressMunicipality": "Praha 5",
    "addressZip": "15500"
  },
  "currency": "CZK",
  "status": "DONE",
  "source": "ANDROID_RECEIPT_UPLOAD",
  "exchangeRate": null,
  "items": [
    {
      "name": "Kuřecí prsa 500g",
      "pricePerUnit": 100.76,
      "quantity": 2.0,
      "itemCategory": "Meat",
      "quantityUnit": "ks",
      "subTotal": 183.2,
      "tax": 18.32,
      "taxPercentage": 10.0,
      "priceIncludingTax": 201.52,
      "discount": null,
      "discountDescriptive": "",
      "priceTotal": 201.52,
      "success": true,
      "index": 0,
      "notices": []
    },
    {
      "name": "Smetana 33% 250ml",
      "pricePerUnit": 25.43,
      "quantity": 1.0,
      "itemCategory": "Dairy Products",
      "quantityUnit": "ks",
      "subTotal": 23.12,
      "tax": 2.31,
      "taxPercentage": 10.0,
      "priceIncludingTax": 25.43,
      "discount": null,
      "discountDescriptive": "",
      "priceTotal": 25.43,
      "success": true,
      "index": 1,
      "notices": []
    },
    {
      "name": "Sušenky Oreo 154g",
      "pricePerUnit": 38.2,
      "quantity": 1.0,
      "itemCategory": "Snacks",
      "quantityUnit": "ks",
      "subTotal": 31.57,
      "tax": 6.63,
      "taxPercentage": 21.0,
      "priceIncludingTax": 38.2,
      "discount": null,
      "discountDescriptive": "",
      "priceTotal": 38.2,
      "success": true,
      "index": 2,
      "notices": []
    },
    {
      "name": "Müsli tyčinka",
      "pricePerUnit": 12.78,
      "quantity": 2.0,
      "itemCategory": "Snacks",
      "quantityUnit": "ks",
      "subTotal": 23.24,
      "tax": 2.32,
      "taxPercentage": 10.0,
      "priceIncludingTax": 25.56,
      "discount": null,
      "discountDescriptive": "",
      "priceTotal": 25.56,
      "success": true,
      "index": 3,
      "notices": []
    }
  ],
  "notices": []
}