{
  "receipt_id": "91ccc9ae-e34c-4150-a61c-3806ba69c4a9",
  "moneyAmount": 1402.1,
  "amountFromDocument": 1402.1,
  "subTotal": 1236.88,
  "totalTax": 165.22,
  "priceIncludingTax": 1402.1,
  "discount": 0.0,
  "timeFromReceipt": "2024-01-05T19:49:00",
  "company": {
    "name": "BILLA, spol. s r.o.",
    "companyCountryCode": "CZ"
  },
  "shop": {
    "addressStreet": "Sokolovská",
    "addressStreetNumber": "394/17",
    "addressMunicipality": "Praha 8",
    "addressZip": "18600"
  },
  "currency": "CZK",
  "status": "DONE",
  "source": "ANDROID_RECEIPT_UPLOAD",
  "exchangeRate": null,
  "items": [
    {
      "name": "Jogurt bílý 150g",
      "pricePerUnit": 9.17,
      "quantity": 1.0,
      "itemCategory": "Dairy Products",
      "quantityUnit": "ks",
      "subTotal": 7.58,
      "tax": 1.59,
      "taxPercentage": 21.0,
      "priceIncludingTax": 9.17,
      "discount": null,
      "discountDescriptive": "",
      "priceTotal": 9.17,
      "success": true,
      "index": 0,
      "notices": []
    },
    {
      "name": "Müsli tyčinka",
      "pricePerUnit": 11.1,
      "quantity": 2.0,
      "itemCategory": "Snacks",
      "quantityUnit": "ks",
      "subTotal": 20.18,
      "tax": 2.02,
      "taxPercentage": 10.0,
      "priceIncludingTax": 22.2,
      "discount": null,
      "discountDescriptive": "",
      "priceTotal": 22.2,
      "success": true,
      "index": 1,
      "notices": []
    },
    {
      "name": "Šunka výběrová 100g",
      "pricePerUnit": 25.69,
      "quantity": 1.0,
      "itemCategory": "Meat Products",
      "quantityUnit": "ks",
      "subTotal": 21.23,
      "tax": 4.46,
      "taxPercentage": 21.0,
      "priceIncludingTax": 25.69,
      "discount": null,
      "discountDescriptive": "",
      "priceTotal": 25.69,
      "success": true,
      "index": 2,
      "notices": []
    },
    {
      "name": "Papriky červené 500g",
      "pricePerUnit": 37.86,
      "quantity": 3.0,
      "itemCategory": "Vegetables",
      "quantityUnit": "ks",
      "subTotal": 103.25,
      "tax": 10.33,
      "taxPercentage": 10.0,
      "priceIncludingTax": 113.58,
      "discount": null,
      "discountDescriptive": "",
      "priceTotal": 113.58,
      "success": true,
      "index": 3,
      "notices": []
    },
    {
      "name": "Pomeranče síťka 1kg",
      "pricePerUnit": 41.47,
      "quantity": 1.0,
      "itemCategory": "Fresh Products",
      "quantityUnit": "ks",
      "subTotal": 37.7,
      "tax": 3.77,
      "taxPercentage": 10.0,
      "priceIncludingTax": 41.47,
      "discount": null,
      "discountDescriptive": "",
      "priceTotal": 41.47,
      "success": true,
      "index": 4,
      "notices": []
    },
    {
      "name": "Müsli tyčinka",
      "pricePerUnit": 11.19,
      "quantity": 1.0,
      "itemCategory": "Snacks",
      "quantityUnit": "ks",
      "subTotal": 10.17,
      "tax": 1.02,
      "taxPercentage": 10.0,
      "priceIncludingTax": 11.19,
      "discount": null,
      "discountDescriptive": "",
      "priceTotal": 11.19,
      "success": true,
      "index": 5,
      "notices": []
    },
    {
      "name": "Kuřecí prsa 500g",
      "pricePerUnit": 89.91,
      "quantity": 2.0,
      "itemCategory": "Meat",
      "quantityUnit": "ks",
      "subTotal": 163.47,
      "tax": 16.35,
      "taxPercentage": 10.0,
      "priceIncludingTax": 179.82,
      "discount": null,
      "discountDescriptive": "",
      "priceTotal": 179.82,
      "success": true,
      "index": 6,
      "notices": []
    },
    {
      "name": "Jablka Golden 2kg",
      "pricePerUnit": 68.61,
      "quantity": 2.0,
      "itemCategory": "Fresh Products",
      "quantityUnit": "ks",
      "subTotal": 119.32,
      "tax": 17.9,
      "taxPercentage": 15.0,
      "priceIncludingTax": 137.22,
      "discount": null,
      "discountDescriptive": "",
      "priceTotal": 137.22,
      "success": true,
      "index": 7,
      "notices": []
    },
    {
      "name": "Papriky červené 500g",
      "pricePerUnit": 34.74,
      "quantity": 2.0,
      "itemCategory": "Vegetables",
      "quantityUnit": "ks",
      "subTotal": 63.16,
      "tax": 6.32,
      "taxPercentage": 10.0,
      "priceIncludingTax": 69.48,
      "discount": null,
      "discountDescriptive": "",
      "priceTotal": 69.48,
      "success": true,
      "index": 8,
      "notices": []
    },
    {
      "name": "Chips Lay's 130g",
      "pricePerUnit": 26.43,
      "quantity": 1.0,
      "itemCategory": "Snacks",
      "quantityUnit": "ks",
      "subTotal": 21.84,
      "tax": 4.59,
      "taxPercentage": 21.0,
      "priceIncludingTax": 26.43,
      "discount": null,
      "discountDescriptive": "",
      "priceTotal": 26.43,
      "success": true,
      "index": 9,
      "notices": []
    },
    {
      "name": "Mozzarella 125g",
      "pricePerUnit": 33.48,
      "quantity": 1.0,
      "itemCategory": "Dairy Products",
      "quantityUnit": "ks",
      "subTotal": 29.11,
      "tax": 4.37,
      "taxPercentage": 15.0,
      "priceIncludingTax": 33.48,
      "discount": null,
      "discountDescriptive": "",
      "priceTotal": 33.48,
      "success": true,
      "index": 10,
      "notices": []
    },
    {
      "name": "Šunka výběrová 100g",
      "pricePerUnit": 31.56,
      "quantity": 2.0,
      "itemCategory": "Meat Products",
      "quantityUnit": "ks",
      "subTotal": 57.38,
      "tax": 5.74,
      "taxPercentage": 10.0,
      "priceIncludingTax": 63.12,
      "discount": null,
      "discountDescriptive": "",
      "priceTotal": 63.12,
      "success": true,
      "index": 11,
      "notices": []
    },
    {
      "name": "Eidam 45% 100g",
      "pricePerUnit": 18.81,
      "quantity": 1.0,
      "itemCategory": "Dairy Products",
      "quantityUnit": "ks",
      "subTotal": 16.36,
      "tax": 2.45,
      "taxPercentage": 15.0,
      "priceIncludingTax": 18.81,
      "discount": null,
      "discountDescriptive": "",
      "priceTotal": 18.81,
      "success": true,
      "index": 12,
      "notices": []
    },
    {
      "name": "Chips Lay's 130g",
      "pricePerUnit": 26.58,
      "quantity": 1.0,
      "itemCategory": "Snacks",
      "quantityUnit": "ks",
      "subTotal": 21.97,
      "tax": 4.61,
      "taxPercentage": 21.0,
      "priceIncludingTax": 26.58,
      "discount": null,
      "discountDescriptive": "",
      "priceTotal": 26.58,
      "success": true,
      "index": 13,
      "notices": []
    },
    {
      "name": "Sušenky Oreo 154g",
      "pricePerUnit": 37.62,
      "quantity": 1.0,
      "itemCategory": "Snacks",
      "quantityUnit": "ks",
      "subTotal": 32.71,
      "tax": 4.91,
      "taxPercentage": 15.0,
      "priceIncludingTax": 37.62,
      "discount": null,
      "discountDescriptive": "",
      "priceTotal": 37.62,
      "success": true,
      "index": 14,
      "notices": []
    },
    {
      "name": "Cottage sýr 180g",
      "pricePerUnit": 26.79,
      "quantity": 1.0,
      "itemCategory": "Dairy Products",
      "quantityUnit": "ks",
      "subTotal": 23.3,
      "tax": 3.49,
      "taxPercentage": 15.0,
      "priceIncludingTax": 26.79,
      "discount": null,
      "discountDescriptive": "",
      "priceTotal": 26.79,
      "success": true,
      "index": 15,
      "notices": []
    },
    {
      "name": "Olivový olej 0,5l",
      "pricePerUnit": 89.98,
      "quantity": 1.0,
      "itemCategory": "Food and Drink",
      "quantityUnit": "ks",
      "subTotal": 74.36,
      "tax": 15.62,
      "taxPercentage": 21.0,
      "priceIncludingTax": 89.98,
      "discount": null,
      "discountDescriptive": "",
      "priceTotal": 89.98,
      "success": true,
      "index": 16,
      "notices": []
    },
    {
      "name": "Rýže dlouhozrnná 1kg",
      "pricePerUnit": 29.74,
      "quantity": 3.0,
      "itemCategory": "Food and Drink",
      "quantityUnit": "ks",
      "subTotal": 77.58,
      "tax": 11.64,
      "taxPercentage": 15.0,
      "priceIncludingTax": 89.22,
      "discount": null,
      "discountDescriptive": "",
      "priceTotal": 89.22,
      "success": true,
      "index": 17,
      "notices": []
    },
    {
      "name": "Chléb konzumní",
      "pricePerUnit": 33.61,
      "quantity": 1.0,
      "itemCategory": "Bakery",
      "quantityUnit": "ks",
      "subTotal": 29.23,
      "tax": 4.38,
      "taxPercentage": 15.0,
      "priceIncludingTax": 33.61,
      "discount": null,
      "discountDescriptive": "",
      "priceTotal": 33.61,
      "success": true,
      "index": 18,
      "notices": []
    },
    {
      "name": "Rohlík sezamový",
      "pricePerUnit": 2.98,
      "quantity": 1.0,
      "itemCategory": "Bakery",
      "quantityUnit": "ks",
      "subTotal": 2.46,
      "tax": 0.52,
      "taxPercentage": 21.0,
      "priceIncludingTax": 2.98,
      "discount": null,
      "discountDescriptive": "",
      "priceTotal": 2.98,
      "success": true,
      "index": 19,
      "notices": []
    },
    {
      "name": "Cibule žlutá 1kg",
      "pricePerUnit": 21.05,
      "quantity": 1.0,
      "itemCategory": "Vegetables",
      "quantityUnit": "ks",
      "subTotal": 17.4,
      "tax": 3.65,
      "taxPercentage": 21.0,
      "priceIncludingTax": 21.05,
      "discount": null,
      "discountDescriptive": "",
      "priceTotal": 21.05,
      "success": true,
      "index": 20,
      "notices": []
    },
    {
      "name": "Rýže dlouhozrnná 1kg",
      "pricePerUnit": 26.97,
      "quantity": 1.0,
      "itemCategory": "Food and Drink",
      "quantityUnit": "ks",
      "subTotal": 24.52,
      "tax": 2.45,
      "taxPercentage": 10.0,
      "priceIncludingTax": 26.97,
      "discount": null,
      "discountDescriptive": "",
      "priceTotal": 26.97,
      "success": true,
      "index": 21,
      "notices": []
    },
    {
      "name": "Těstoviny penne 500g",
      "pricePerUnit": 24.78,
      "quantity": 1.0,
      "itemCategory": "Food and Drink",
      "quantityUnit": "ks",
      "subTotal": 22.53,
      "tax": 2.25,
      "taxPercentage": 10.0,
      "priceIncludingTax": 24.78,
      "discount": null,
      "discountDescriptive": "",
      "priceTotal": 24.78,
      "success": true,
      "index": 22,
      "notices": []
    },
    {
      "name": "Pivo Pilsner 0,5l",
      "pricePerUnit": 17.86,
      "quantity": 1.0,
      "itemCategory": "Beverages",
      "quantityUnit": "ks",
      "subTotal": 14.76,
      "tax": 3.1,
      "taxPercentage": 21.0,
      "priceIncludingTax": 17.86,
      "discount": null,
      "discountDescriptive": "",
      "priceTotal": 17.86,
      "success": true,
      "index": 23,
      "notices": []
    },
    {
      "name": "Kinder Bueno",
      "pricePerUnit": 20.12,
      "quantity": 1.0,
      "itemCategory": "Snacks",
      "quantityUnit": "ks",
      "subTotal": 16.63,
      "tax": 3.49,
      "taxPercentage": 21.0,
      "priceIncludingTax": 20.12,
      "discount": null,
      "discountDescriptive": "",
      "priceTotal": 20.12,
      "success": true,
      "index": 24,
      "notices": []
    },
    {
      "name": "Mozzarella 125g",
      "pricePerUnit": 38.24,
      "quantity": 2.0,
      "itemCategory": "Dairy Products",
      "quantityUnit": "ks",
      "subTotal": 66.5,
      "tax": 9.98,
      "taxPercentage": 15.0,
      "priceIncludingTax": 76.48,
      "discount": null,
      "discountDescriptive": "",
      "priceTotal": 76.48,
      "success": true,
      "index": 25,
      "notices": []
    },
    {
      "name": "Čokoláda Milka 100g",
      "pricePerUnit": 26.48,
      "quantity": 1.0,
      "itemCategory": "Snacks",
      "quantityUnit": "ks",
      "subTotal": 24.07,
      "tax": 2.41,
      "taxPercentage": 10.0,
      "priceIncludingTax": 26.48,
      "discount": null,
      "discountDescriptive": "",
      "priceTotal": 26.48,
      "success": true,
      "index": 26,
      "notices": []
    },
    {
      "name": "Sáčky do koše 30ks",
      "pricePerUnit": 38.56,
      "quantity": 1.0,
      "itemCategory": "Household Supplies",
      "quantityUnit": "ks",
      "subTotal": 35.05,
      "tax": 3.51,
      "taxPercentage": 10.0,
      "priceIncludingTax": 38.56,
      "discount": null,
      "discountDescriptive": "",
      "priceTotal": 38.56,
      "success": true,
      "index": 27,
      "notices": []
    },
    {
      "name": "Chléb konzumní",
      "pricePerUnit": 32.41,
      "quantity": 2.0,
      "itemCategory": "Bakery",
      "quantityUnit": "ks",
      "subTotal": 58.93,
      "tax": 5.89,
      "taxPercentage": 10.0,
      "priceIncludingTax": 64.82,
      "discount": null,
      "discountDescriptive": "",
      "priceTotal": 64.82,
      "success": true,
      "index": 28,
      "notices": []
    },
    {
      "name": "Smetana 33% 250ml",
      "pricePerUnit": 26.54,
      "quantity": 1.0,
      "itemCategory": "Dairy Products",
      "quantityUnit": "ks",
      "subTotal": 24.13,
      "tax": 2.41,
      "taxPercentage": 10.0,
      "priceIncludingTax": 26.54,
      "discount": null,
      "discountDescriptive": "",
      "priceTotal": 26.54,
      "success": true,
      "index": 29,
      "notices": []
    }
  ],
  "notices": []
}