{
  "receipt_id": "ba9d8e87-7427-4c76-964e-a35d9338fc72",
  "moneyAmount": 1478.45,
  "amountFromDocument": 1478.45,
  "subTotal": 1284.05,
  "totalTax": 194.4,
  "priceIncludingTax": 1478.45,
  "discount": 0.0,
  "timeFromReceipt": "2024-07-21T16:53:00",
  "company": {
    "name": "Lidl Česká republika v.o.s.",
    "companyCountryCode": "CZ"
  },
  "shop": {
    "addressStreet": "Sokolovská",
    "addressStreetNumber": "394/17",
    "addressMunicipality": "Praha 8",
    "addressZip": "18600"
  },
  "currency": "CZK",
  "status": "DONE",
  "source": "ANDROID_RECEIPT_UPLOAD",
  "exchangeRate": null,
  "items": [
    {
      "name": "Aviváž Lenor 1l",
      "pricePerUnit": 91.72,
      "quantity": 1.0,
      "itemCategory": "Household Supplies",
      "quantityUnit": "ks",
      "subTotal": 83.38,
      "tax": 8.34,
      "taxPercentage": 10.0,
      "priceIncludingTax": 91.72,
      "discount": null,
      "discountDescriptive": "",
      "priceTotal": 91.72,
      "success": true,
      "index": 0,
      "notices": []
    },
    {
      "name": "Cottage sýr 180g",
      "pricePerUnit": 33.6,
      "quantity": 3.0,
      "itemCategory": "Dairy Products",
      "quantityUnit": "ks",
      "subTotal": 87.65,
      "tax": 13.15,
      "taxPercentage": 15.0,
      "priceIncludingTax": 100.8,
      "discount": null,
      "discountDescriptive": "",
      "priceTotal": 100.8,
      "success": true,
      "index": 1,
      "notices": []
    },
    {
      "name": "Chléb konzumní",
      "pricePerUnit": 29.96,
      "quantity": 2.0,
      "itemCategory": "Bakery",
      "quantityUnit": "ks",
      "subTotal": 54.47,
      "tax": 5.45,
      "taxPercentage": 10.0,
      "priceIncludingTax": 59.92,
      "discount": null,
      "discountDescriptive": "",
      "priceTotal": 59.92,
      "success": true,
      "index": 2,
      "notices": []
    },
    {
      "name": "Mléko plnotučné 1l",
      "pricePerUnit": 24.4,
      "quantity": 1.0,
      "itemCategory": "Dairy Products",
      "quantityUnit": "ks",
      "subTotal": 22.18,
      "tax": 2.22,
      "taxPercentage": 10.0,
      "priceIncludingTax": 24.4,
      "discount": null,
      "discountDescriptive": "",
      "priceTotal": 24.4,
      "success": true,
      "index": 3,
      "notices": []
    },
    {
      "name": "Sušenky Oreo 154g",
      "pricePerUnit": 30.32,
      "quantity": 2.0,
      "itemCategory": "Snacks",
      "quantityUnit": "ks",
      "subTotal": 55.13,
      "tax": 5.51,
      "taxPercentage": 10.0,
      "priceIncludingTax": 60.64,
      "discount": null,
      "discountDescriptive": "",
      "priceTotal": 60.64,
      "success": true,
      "index": 4,
      "notices": []
    },
    {
      "name": "Jogurt bílý 150g",
      "pricePerUnit": 9.88,
      "quantity": 1.0,
      "itemCategory": "Dairy Products",
      "quantityUnit": "ks",
      "subTotal": 8.59,
      "tax": 1.29,
      "taxPercentage": 15.0,
      "priceIncludingTax": 9.88,
      "discount": null,
      "discountDescriptive": "",
      "priceTotal": 9.88,
      "success": true,
      "index": 5,
      "notices": []
    },
    {
      "name": "Ricotta 250g",
      "pricePerUnit": 41.58,
      "quantity": 1.0,
      "itemCategory": "Dairy Products",
      "quantityUnit": "ks",
      "subTotal": 34.36,
      "tax": 7.22,
      "taxPercentage": 21.0,
      "priceIncludingTax": 41.58,
      "discount": null,
      "discountDescriptive": "",
      "priceTotal": 41.58,
      "success": true,
      "index": 6,
      "notices": []
    },
    {
      "name": "Bageta",
      "pricePerUnit": 19.25,
      "quantity": 1.0,
      "itemCategory": "Bakery",
      "quantityUnit": "ks",
      "subTotal": 17.5,
      "tax": 1.75,
      "taxPercentage": 10.0,
      "priceIncludingTax": 19.25,
      "discount": null,
      "discountDescriptive": "",
      "priceTotal": 19.25,
      "success": true,
      "index": 7,
      "notices": []
    },
    {
      "name": "Kinder Bueno",
      "pricePerUnit": 22.72,
      "quantity": 1.0,
      "itemCategory": "Snacks",
      "quantityUnit": "ks",
      "subTotal": 18.78,
      "tax": 3.94,
      "taxPercentage": 21.0,
      "priceIncludingTax": 22.72,
      "discount": null,
      "discountDescriptive": "",
      "priceTotal": 22.72,
      "success": true,
      "index": 8,
      "notices": []
    },
    {
      "name": "Minerální voda 1,5l",
      "pricePerUnit": 13.37,
      "quantity": 1.0,
      "itemCategory": "Beverages",
      "quantityUnit": "ks",
      "subTotal": 11.05,
      "tax": 2.32,
      "taxPercentage": 21.0,
      "priceIncludingTax": 13.37,
      "discount": null,
      "discountDescriptive": "",
      "priceTotal": 13.37,
      "success": true,
      "index": 9,
      "notices": []
    },
    {
      "name": "Bageta",
      "pricePerUnit": 20.88,
      "quantity": 1.0,
      "itemCategory": "Bakery",
      "quantityUnit": "ks",
      "subTotal": 18.16,
      "tax": 2.72,
      "taxPercentage": 15.0,
      "priceIncludingTax": 20.88,
      "discount": null,
      "discountDescriptive": "",
      "priceTotal": 20.88,
      "success": true,
      "index": 10,
      "notices": []
    },
    {
      "name": "Okurka salátová 1ks",
      "pricePerUnit": 14.19,
      "quantity": 1.0,
      "itemCategory": "Vegetables",
      "quantityUnit": "ks",
      "subTotal": 11.73,
      "tax": 2.46,
      "taxPercentage": 21.0,
      "priceIncludingTax": 14.19,
      "discount": null,
      "discountDescriptive": "",
      "priceTotal": 14.19,
      "success": true,
      "index": 11,
      "notices": []
    },
    {
      "name": "Smetana 33% 250ml",
      "pricePerUnit": 30.12,
      "quantity": 1.0,
      "itemCategory": "Dairy Products",
      "quantityUnit": "ks",
      "subTotal": 24.89,
      "tax": 5.23,
      "taxPercentage": 21.0,
      "priceIncludingTax": 30.12,
      "discount": null,
      "discountDescriptive": "",
      "priceTotal": 30.12,
      "success": true,
      "index": 12,
      "notices": []
    },
    {
      "name": "Uzená klobása 200g",
      "pricePerUnit": 39.5,
      "quantity": 1.0,
      "itemCategory": "Meat Products",
      "quantityUnit": "ks",
      "subTotal": 32.64,
      "tax": 6.86,
      "taxPercentage": 21.0,
      "priceIncludingTax": 39.5,
      "discount": null,
      "discountDescriptive": "",
      "priceTotal": 39.5,
      "success": true,
      "index": 13,
      "notices": []
    },
    {
      "name": "Džus pomeranč 1l",
      "pricePerUnit": 43.94,
      "quantity": 1.0,
      "itemCategory": "Beverages",
      "quantityUnit": "ks",
      "subTotal": 39.95,
      "tax": 3.99,
      "taxPercentage": 10.0,
      "priceIncludingTax": 43.94,
      "discount": null,
      "discountDescriptive": "",
      "priceTotal": 43.94,
      "success": true,
      "index": 14,
      "notices": []
    },
    {
      "name": "Rohlik",
      "pricePerUnit": 3.32,
      "quantity": 1.0,
      "itemCategory": "Bakery",
      "quantityUnit": "ks",
      "subTotal": 2.89,
      "tax": 0.43,
      "taxPercentage": 15.0,
      "priceIncludingTax": 3.32,
      "discount": null,
      "discountDescriptive": "",
      "priceTotal": 3.32,
      "success": true,
      "index": 15,
      "notices": []
    },
    {
      "name": "Okurka salátová 1ks",
      "pricePerUnit": 11.51,
      "quantity": 1.0,
      "itemCategory": "Vegetables",
      "quantityUnit": "ks",
      "subTotal": 9.51,
      "tax": 2.0,
      "taxPercentage": 21.0,
      "priceIncludingTax": 11.51,
      "discount": null,
      "discountDescriptive": "",
      "priceTotal": 11.51,
      "success": true,
      "index": 16,
      "notices": []
    },
    {
      "name": "Banány 1kg",
      "pricePerUnit": 32.3,
      "quantity": 2.0,
      "itemCategory": "Fresh Products",
      "quantityUnit": "ks",
      "subTotal": 58.73,
      "tax": 5.87,
      "taxPercentage": 10.0,
      "priceIncludingTax": 64.6,
      "discount": null,
      "discountDescriptive": "",
      "priceTotal": 64.6,
      "success": true,
      "index": 17,
      "notices": []
    },
    {
      "name": "Těstoviny penne 500g",
      "pricePerUnit": 23.0,
      "quantity": 1.0,
      "itemCategory": "Food and Drink",
      "quantityUnit": "ks",
      "subTotal": 20.91,
      "tax": 2.09,
      "taxPercentage": 10.0,
      "priceIncludingTax": 23.0,
      "discount": null,
      "discountDescriptive": "",
      "priceTotal": 23.0,
      "success": true,
      "index": 18,
      "notices": []
    },
    {
      "name": "Snickers 50g",
      "pricePerUnit": 13.68,
      "quantity": 2.0,
      "itemCategory": "Snacks",
      "quantityUnit": "ks",
      "subTotal": 22.61,
      "tax": 4.75,
      "taxPercentage": 21.0,
      "priceIncludingTax": 27.36,
      "discount": null,
      "discountDescriptive": "",
      "priceTotal": 27.36,
      "success": true,
      "index": 19,
      "notices": []
    },
    {
      "name": "Toaletní papír 8ks",
      "pricePerUnit": 56.67,
      "quantity": 3.0,
      "itemCategory": "Household Supplies",
      "quantityUnit": "ks",
      "subTotal": 147.83,
      "tax": 22.18,
      "taxPercentage": 15.0,
      "priceIncludingTax": 170.01,
      "discount": null,
      "discountDescriptive": "",
      "priceTotal": 170.01,
      "success": true,
      "index": 20,
      "notices": []
    },
    {
      "name": "Chléb konzumní",
      "pricePerUnit": 29.88,
      "quantity": 1.0,
      "itemCategory": "Bakery",
      "quantityUnit": "ks",
      "subTotal": 24.69,
      "tax": 5.19,
      "taxPercentage": 21.0,
      "priceIncludingTax": 29.88,
      "discount": null,
      "discountDescriptive": "",
      "priceTotal": 29.88,
      "success": true,
      "index": 21,
      "notices": []
    },
    {
      "name": "Mozzarella 125g",
      "pricePerUnit": 39.73,
      "quantity": 1.0,
      "itemCategory": "Dairy Products",
      "quantityUnit": "ks",
      "subTotal": 36.12,
      "tax": 3.61,
      "taxPercentage": 10.0,
      "priceIncludingTax": 39.73,
      "discount": null,
      "discountDescriptive": "",
      "priceTotal": 39.73,
      "success": true,
      "index": 22,
      "notices": []
    },
    {
      "name": "Uzená klobása 200g",
      "pricePerUnit": 35.77,
      "quantity": 2.0,
      "itemCategory": "Meat Products",
      "quantityUnit": "ks",
      "subTotal": 65.04,
      "tax": 6.5,
      "taxPercentage": 10.0,
      "priceIncludingTax": 71.54,
      "discount": null,
      "discountDescriptive": "",
      "priceTotal": 71.54,
      "success": true,
      "index": 23,
      "notices": []
    },
    {
      "name": "Šunka výběrová 100g",
      "pricePerUnit": 31.61,
      "quantity": 3.0,
      "itemCategory": "Meat Products",
      "quantityUnit": "ks",
      "subTotal": 78.37,
      "tax": 16.46,
      "taxPercentage": 21.0,
      "priceIncludingTax": 94.83,
      "discount": null,
      "discountDescriptive": "",
      "priceTotal": 94.83,
      "success": true,
      "index": 24,
      "notices": []
    },
    {
      "name": "Bageta",
      "pricePerUnit": 17.69,
      "quantity": 1.0,
      "itemCategory": "Bakery",
      "quantityUnit": "ks",
      "subTotal": 16.08,
      "tax": 1.61,
      "taxPercentage": 10.0,
      "priceIncludingTax": 17.69,
      "discount": null,
      "discountDescriptive": "",
      "priceTotal": 17.69,
      "success": true,
      "index": 25,
      "notices": []
    },
    {
      "name": "Jar prostředek 500ml",
      "pricePerUnit": 43.23,
      "quantity": 2.0,
      "itemCategory": "Household Supplies",
      "quantityUnit": "ks",
      "subTotal": 75.18,
      "tax": 11.28,
      "taxPercentage": 15.0,
      "priceIncludingTax": 86.46,
      "discount": null,
      "discountDescriptive": "",
      "priceTotal": 86.46,
      "success": true,
      "index": 26,
      "notices": []
    },
    {
      "name": "Müsli tyčinka",
      "pricePerUnit": 12.61,
      "quantity": 2.0,
      "itemCategory": "Snacks",
      "quantityUnit": "ks",
      "subTotal": 21.93,
      "tax": 3.29,
      "taxPercentage": 15.0,
      "priceIncludingTax": 25.22,
      "discount": null,
      "discountDescriptive": "",
      "priceTotal": 25.22,
      "success": true,
      "index": 27,
      "notices": []
    },
    {
      "name": "Cibule žlutá 1kg",
      "pricePerUnit": 18.75,
      "quantity": 1.0,
      "itemCategory": "Vegetables",
      "quantityUnit": "ks",
      "subTotal": 17.05,
      "tax": 1.7,
      "taxPercentage": 10.0,
      "priceIncludingTax": 18.75,
      "discount": null,
      "discountDescriptive": "",
      "priceTotal": 18.75,
      "success": true,
      "index": 28,
      "notices": []
    },
    {
      "name": "Toaletní papír 8ks",
      "pricePerUnit": 60.08,
      "quantity": 2.0,
      "itemCategory": "Household Supplies",
      "quantityUnit": "ks",
      "subTotal": 99.31,
      "tax": 20.85,
      "taxPercentage": 21.0,
      "priceIncludingTax": 120.16,
      "discount": null,
      "discountDescriptive": "",
      "priceTotal": 120.16,
      "success": true,
      "index": 29,
      "notices": []
    },
    {
      "name": "Pivo Pilsner 0,5l",
      "pricePerUnit": 16.98,
      "quantity": 1.0,
      "itemCategory": "Beverages",
      "quantityUnit": "ks",
      "subTotal": 14.03,
      "tax": 2.95,
      "taxPercentage": 21.0,
      "priceIncludingTax": 16.98,
      "discount": null,
      "discountDescriptive": "",
      "priceTotal": 16.98,
      "success": true,
      "index": 30,
      "notices": []
    },
    {
      "name": "Sušenky Oreo 154g",
      "pricePerUnit": 30.31,
      "quantity": 1.0,
      "itemCategory": "Snacks",
      "quantityUnit": "ks",
      "subTotal": 25.05,
      "tax": 5.26,
      "taxPercentage": 21.0,
      "priceIncludingTax": 30.31,
      "discount": null,
      "discountDescriptive": "",
      "priceTotal": 30.31,
      "success": true,
      "index": 31,
      "notices": []
    },
    {
      "name": "Papriky červené 500g",
      "pricePerUnit": 34.19,
      "quantity": 1.0,
      "itemCategory": "Vegetables",
      "quantityUnit": "ks",
      "subTotal": 28.26,
      "tax": 5.93,
      "taxPercentage": 21.0,
      "priceIncludingTax": 34.19,
      "discount": null,
      "discountDescriptive": "",
      "priceTotal": 34.19,
      "success": true,
      "index": 32,
      "notices": []
    }
  ],
  "notices": []
}